{
"meta":{"test_sets":[],"test_metrics":[],"learn_metrics":[{"best_value":"Min","name":"RMSE"}],"launch_mode":"Train","parameters":"","iteration_count":1000,"learn_sets":["learn"],"name":"experiment"},
"iterations":[
{"learn":[9.108590302],"iteration":0,"passed_time":0.1421010542,"remaining_time":141.9589532},
{"learn":[8.90813426],"iteration":1,"passed_time":0.1463328154,"remaining_time":73.02007486},
{"learn":[8.718125354],"iteration":2,"passed_time":0.1583263008,"remaining_time":52.61710731},
{"learn":[8.552223655],"iteration":3,"passed_time":0.1707571708,"remaining_time":42.51853552},
{"learn":[8.405425649],"iteration":4,"passed_time":0.1757742492,"remaining_time":34.97907559},
{"learn":[8.238583428],"iteration":5,"passed_time":0.1834325914,"remaining_time":30.38866597},
{"learn":[8.075592606],"iteration":6,"passed_time":0.1895497812,"remaining_time":26.88899039},
{"learn":[7.920581333],"iteration":7,"passed_time":0.1940264925,"remaining_time":24.05928507},
{"learn":[7.778321164],"iteration":8,"passed_time":0.1976694124,"remaining_time":21.76559863},
{"learn":[7.618784576],"iteration":9,"passed_time":0.2023039462,"remaining_time":20.02809068},
{"learn":[7.485125777],"iteration":10,"passed_time":0.205018932,"remaining_time":18.43306579},
{"learn":[7.331646071],"iteration":11,"passed_time":0.2110031301,"remaining_time":17.37259104},
{"learn":[7.184402476],"iteration":12,"passed_time":0.2153908654,"remaining_time":16.35313724},
{"learn":[7.042328582],"iteration":13,"passed_time":0.2177932338,"remaining_time":15.33886633},
{"learn":[6.913553563],"iteration":14,"passed_time":0.2219287667,"remaining_time":14.57332235},
{"learn":[6.783347878],"iteration":15,"passed_time":0.2248296808,"remaining_time":13.82702537},
{"learn":[6.655745273],"iteration":16,"passed_time":0.227711346,"remaining_time":13.16707371},
{"learn":[6.534722222],"iteration":17,"passed_time":0.2311606057,"remaining_time":12.61109527},
{"learn":[6.420643473],"iteration":18,"passed_time":0.2370417757,"remaining_time":12.23884115},
{"learn":[6.305501053],"iteration":19,"passed_time":0.2403278158,"remaining_time":11.77606298},
{"learn":[6.189096665],"iteration":20,"passed_time":0.2425119001,"remaining_time":11.30567382},
{"learn":[6.079084011],"iteration":21,"passed_time":0.2451806813,"remaining_time":10.89939574},
{"learn":[5.985403401],"iteration":22,"passed_time":0.2474683687,"remaining_time":10.51202592},
{"learn":[5.894854682],"iteration":23,"passed_time":0.2504141818,"remaining_time":10.18351006},
{"learn":[5.807992659],"iteration":24,"passed_time":0.2540630269,"remaining_time":9.908458047},
{"learn":[5.711032385],"iteration":25,"passed_time":0.2562720503,"remaining_time":9.600345269},
{"learn":[5.628969971],"iteration":26,"passed_time":0.2595028539,"remaining_time":9.351713958},
{"learn":[5.549743646],"iteration":27,"passed_time":0.2623687251,"remaining_time":9.107942886},
{"learn":[5.463017946],"iteration":28,"passed_time":0.2673719942,"remaining_time":8.952351942},
{"learn":[5.374514761],"iteration":29,"passed_time":0.2698242931,"remaining_time":8.724318811},
{"learn":[5.289213119],"iteration":30,"passed_time":0.2721902516,"remaining_time":8.508140447},
{"learn":[5.212770449],"iteration":31,"passed_time":0.2743862126,"remaining_time":8.300182932},
{"learn":[5.148392689],"iteration":32,"passed_time":0.2764347733,"remaining_time":8.100376538},
{"learn":[5.077661429],"iteration":33,"passed_time":0.2792543273,"remaining_time":7.93410824},
{"learn":[5.009026695],"iteration":34,"passed_time":0.2817876734,"remaining_time":7.769288711},
{"learn":[4.940661725],"iteration":35,"passed_time":0.2836846845,"remaining_time":7.596445441},
{"learn":[4.880454812],"iteration":36,"passed_time":0.2853221944,"remaining_time":7.426088464},
{"learn":[4.813744998],"iteration":37,"passed_time":0.2870205331,"remaining_time":7.266151391},
{"learn":[4.747035563],"iteration":38,"passed_time":0.2893232274,"remaining_time":7.129221066},
{"learn":[4.673386387],"iteration":39,"passed_time":0.291832795,"remaining_time":7.003987079},
{"learn":[4.609909572],"iteration":40,"passed_time":0.2937681362,"remaining_time":6.871308357},
{"learn":[4.548344801],"iteration":41,"passed_time":0.2954570401,"remaining_time":6.739234391},
{"learn":[4.488661754],"iteration":42,"passed_time":0.2981267827,"remaining_time":6.63505421},
{"learn":[4.436601102],"iteration":43,"passed_time":0.3010165688,"remaining_time":6.540269086},
{"learn":[4.387038014],"iteration":44,"passed_time":0.304319743,"remaining_time":6.458341213},
{"learn":[4.333658264],"iteration":45,"passed_time":0.3060292249,"remaining_time":6.346780012},
{"learn":[4.292102274],"iteration":46,"passed_time":0.3076927309,"remaining_time":6.238961118},
{"learn":[4.245986704],"iteration":47,"passed_time":0.3101759364,"remaining_time":6.151822738},
{"learn":[4.207062731],"iteration":48,"passed_time":0.3116165229,"remaining_time":6.047904352},
{"learn":[4.166551653],"iteration":49,"passed_time":0.3132634089,"remaining_time":5.952004768},
{"learn":[4.121947145],"iteration":50,"passed_time":0.3146918918,"remaining_time":5.85573736},
{"learn":[4.087541024],"iteration":51,"passed_time":0.3163075912,"remaining_time":5.7665307},
{"learn":[4.044059304],"iteration":52,"passed_time":0.3179498631,"remaining_time":5.681104158},
{"learn":[4.00083299],"iteration":53,"passed_time":0.3193397083,"remaining_time":5.594358593},
{"learn":[3.959004692],"iteration":54,"passed_time":0.3209288571,"remaining_time":5.514141273},
{"learn":[3.930282509],"iteration":55,"passed_time":0.3229308133,"remaining_time":5.443690853},
{"learn":[3.896952166],"iteration":56,"passed_time":0.3248204561,"remaining_time":5.373784036},
{"learn":[3.855515868],"iteration":57,"passed_time":0.3262600836,"remaining_time":5.298913771},
{"learn":[3.823060998],"iteration":58,"passed_time":0.3276901262,"remaining_time":5.226379809},
{"learn":[3.784877498],"iteration":59,"passed_time":0.3293092548,"remaining_time":5.159178325},
{"learn":[3.753896315],"iteration":60,"passed_time":0.3307930623,"remaining_time":5.092044025},
{"learn":[3.715060621],"iteration":61,"passed_time":0.3322357461,"remaining_time":5.026405321},
{"learn":[3.685344187],"iteration":62,"passed_time":0.3336782903,"remaining_time":4.962802508},
{"learn":[3.6554275],"iteration":63,"passed_time":0.3355890317,"remaining_time":4.907989589},
{"learn":[3.624985586],"iteration":64,"passed_time":0.3378409,"remaining_time":4.859711407},
{"learn":[3.595468116],"iteration":65,"passed_time":0.3393746348,"remaining_time":4.802665286},
{"learn":[3.565318525],"iteration":66,"passed_time":0.3409884019,"remaining_time":4.748390731},
{"learn":[3.535992507],"iteration":67,"passed_time":0.3423634711,"remaining_time":4.692393457},
{"learn":[3.508219632],"iteration":68,"passed_time":0.3438425005,"remaining_time":4.639382144},
{"learn":[3.481302773],"iteration":69,"passed_time":0.3453460468,"remaining_time":4.588168908},
{"learn":[3.451798003],"iteration":70,"passed_time":0.3468830992,"remaining_time":4.538794354},
{"learn":[3.420609756],"iteration":71,"passed_time":0.3484387188,"remaining_time":4.490987931},
{"learn":[3.398796594],"iteration":72,"passed_time":0.3499693689,"remaining_time":4.444131575},
{"learn":[3.374181884],"iteration":73,"passed_time":0.3520629545,"remaining_time":4.405544539},
{"learn":[3.339563307],"iteration":74,"passed_time":0.3537593607,"remaining_time":4.363032115},
{"learn":[3.321680371],"iteration":75,"passed_time":0.3551353685,"remaining_time":4.317698428},
{"learn":[3.289697247],"iteration":76,"passed_time":0.3565204586,"remaining_time":4.273615367},
{"learn":[3.26682542],"iteration":77,"passed_time":0.35805295,"remaining_time":4.232369485},
{"learn":[3.237407404],"iteration":78,"passed_time":0.3594869581,"remaining_time":4.190980866},
{"learn":[3.212586985],"iteration":79,"passed_time":0.3608918016,"remaining_time":4.150255719},
{"learn":[3.184356527],"iteration":80,"passed_time":0.3623766145,"remaining_time":4.11140875},
{"learn":[3.164931915],"iteration":81,"passed_time":0.3642306133,"remaining_time":4.077606134},
{"learn":[3.143961721],"iteration":82,"passed_time":0.3663203904,"remaining_time":4.04717829},
{"learn":[3.119334272],"iteration":83,"passed_time":0.3680958667,"remaining_time":4.013997784},
{"learn":[3.098248815],"iteration":84,"passed_time":0.3694646293,"remaining_time":3.977178068},
{"learn":[3.074759999],"iteration":85,"passed_time":0.3709550275,"remaining_time":3.942475525},
{"learn":[3.049007054],"iteration":86,"passed_time":0.3724596582,"remaining_time":3.908685839},
{"learn":[3.027005726],"iteration":87,"passed_time":0.3740473204,"remaining_time":3.876490411},
{"learn":[3.013731114],"iteration":88,"passed_time":0.3808818328,"remaining_time":3.898689323},
{"learn":[2.995308125],"iteration":89,"passed_time":0.3830772646,"remaining_time":3.873336787},
{"learn":[2.980222885],"iteration":90,"passed_time":0.3844670364,"remaining_time":3.840445451},
{"learn":[2.958534072],"iteration":91,"passed_time":0.3860339478,"remaining_time":3.809987224},
{"learn":[2.941090015],"iteration":92,"passed_time":0.3876329712,"remaining_time":3.780463494},
{"learn":[2.925590806],"iteration":93,"passed_time":0.389379343,"remaining_time":3.752954093},
{"learn":[2.914933657],"iteration":94,"passed_time":0.3912042395,"remaining_time":3.726735124},
{"learn":[2.900342482],"iteration":95,"passed_time":0.3929412,"remaining_time":3.7001963},
{"learn":[2.885915252],"iteration":96,"passed_time":0.3946656675,"remaining_time":3.674052554},
{"learn":[2.871352354],"iteration":97,"passed_time":0.3962777861,"remaining_time":3.647373092},
{"learn":[2.857328352],"iteration":98,"passed_time":0.3982464066,"remaining_time":3.624444569},
{"learn":[2.847008729],"iteration":99,"passed_time":0.4000467488,"remaining_time":3.600420739},
{"learn":[2.833269772],"iteration":100,"passed_time":0.401454214,"remaining_time":3.573339984},
{"learn":[2.819262075],"iteration":101,"passed_time":0.4030838889,"remaining_time":3.548718943},
{"learn":[2.809253333],"iteration":102,"passed_time":0.404504685,"remaining_time":3.522725266},
{"learn":[2.797563952],"iteration":103,"passed_time":0.4060206141,"remaining_time":3.498023752},
{"learn":[2.783405529],"iteration":104,"passed_time":0.407761011,"remaining_time":3.475677189},
{"learn":[2.771823472],"iteration":105,"passed_time":0.4095641514,"remaining_time":3.454248598},
{"learn":[2.758154178],"iteration":106,"passed_time":0.4111563613,"remaining_time":3.431426455},
{"learn":[2.750997418],"iteration":107,"passed_time":0.4131743709,"remaining_time":3.412514249},
{"learn":[2.741737687],"iteration":108,"passed_time":0.4148563784,"remaining_time":3.391165442},
{"learn":[2.731116777],"iteration":109,"passed_time":0.4172384964,"remaining_time":3.375838744},
{"learn":[2.723616616],"iteration":110,"passed_time":0.4195033343,"remaining_time":3.359805984},
{"learn":[2.715294739],"iteration":111,"passed_time":0.4208542709,"remaining_time":3.336773148},
{"learn":[2.704779421],"iteration":112,"passed_time":0.4225250789,"remaining_time":3.316634912},
{"learn":[2.694534685],"iteration":113,"passed_time":0.4254432359,"remaining_time":3.306514974},
{"learn":[2.68484317],"iteration":114,"passed_time":0.426817331,"remaining_time":3.284637721},
{"learn":[2.679520676],"iteration":115,"passed_time":0.4281841658,"remaining_time":3.263058642},
{"learn":[2.670316659],"iteration":116,"passed_time":0.4295197106,"remaining_time":3.241588927},
{"learn":[2.656847743],"iteration":117,"passed_time":0.4313232292,"remaining_time":3.223958374},
{"learn":[2.64387326],"iteration":118,"passed_time":0.4327560361,"remaining_time":3.203849309},
{"learn":[2.633235893],"iteration":119,"passed_time":0.4341416449,"remaining_time":3.183705396},
{"learn":[2.62398958],"iteration":120,"passed_time":0.4356696444,"remaining_time":3.164905929},
{"learn":[2.614093982],"iteration":121,"passed_time":0.437667138,"remaining_time":3.149768419},
{"learn":[2.606228651],"iteration":122,"passed_time":0.4396308042,"remaining_time":3.134603376},
{"learn":[2.598766966],"iteration":123,"passed_time":0.4410901516,"remaining_time":3.11608849},
{"learn":[2.5867749],"iteration":124,"passed_time":0.4426153986,"remaining_time":3.09830779},
{"learn":[2.576193791],"iteration":125,"passed_time":0.4441481626,"remaining_time":3.080837255},
{"learn":[2.562059051],"iteration":126,"passed_time":0.4456591554,"remaining_time":3.063468052},
{"learn":[2.555455364],"iteration":127,"passed_time":0.4466217396,"remaining_time":3.042610601},
{"learn":[2.542688762],"iteration":128,"passed_time":0.4479996162,"remaining_time":3.024865625},
{"learn":[2.536599594],"iteration":129,"passed_time":0.450268787,"remaining_time":3.013337267},
{"learn":[2.528794589],"iteration":130,"passed_time":0.4528973196,"remaining_time":3.004334128},
{"learn":[2.516425997],"iteration":131,"passed_time":0.455029677,"remaining_time":2.992164846},
{"learn":[2.505694263],"iteration":132,"passed_time":0.457356254,"remaining_time":2.981412573},
{"learn":[2.496297947],"iteration":133,"passed_time":0.4596564397,"remaining_time":2.970615498},
{"learn":[2.489741264],"iteration":134,"passed_time":0.4617380619,"remaining_time":2.958543878},
{"learn":[2.485269869],"iteration":135,"passed_time":0.4641987227,"remaining_time":2.94902718},
{"learn":[2.478282821],"iteration":136,"passed_time":0.4670937131,"remaining_time":2.942349448},
{"learn":[2.47211105],"iteration":137,"passed_time":0.4696797526,"remaining_time":2.933796715},
{"learn":[2.462997943],"iteration":138,"passed_time":0.4722875657,"remaining_time":2.925464706},
{"learn":[2.456043832],"iteration":139,"passed_time":0.4744238726,"remaining_time":2.914318074},
{"learn":[2.444026378],"iteration":140,"passed_time":0.4769330141,"remaining_time":2.905570632},
{"learn":[2.438004135],"iteration":141,"passed_time":0.4793349485,"remaining_time":2.89626328},
{"learn":[2.430530955],"iteration":142,"passed_time":0.4825436287,"remaining_time":2.891887341},
{"learn":[2.42424055],"iteration":143,"passed_time":0.4847208941,"remaining_time":2.881396426},
{"learn":[2.418873594],"iteration":144,"passed_time":0.4872696486,"remaining_time":2.873210686},
{"learn":[2.411351894],"iteration":145,"passed_time":0.4896776387,"remaining_time":2.864278791},
{"learn":[2.409192997],"iteration":146,"passed_time":0.4917551387,"remaining_time":2.853517914},
{"learn":[2.403420855],"iteration":147,"passed_time":0.4942604467,"remaining_time":2.845337166},
{"learn":[2.395094177],"iteration":148,"passed_time":0.497174987,"remaining_time":2.839569892},
{"learn":[2.391499925],"iteration":149,"passed_time":0.4992865236,"remaining_time":2.8292903},
{"learn":[2.386716188],"iteration":150,"passed_time":0.5019044115,"remaining_time":2.821965863},
{"learn":[2.377692342],"iteration":151,"passed_time":0.504235126,"remaining_time":2.813101229},
{"learn":[2.371711209],"iteration":152,"passed_time":0.5065095985,"remaining_time":2.804010653},
{"learn":[2.362120865],"iteration":153,"passed_time":0.5089934103,"remaining_time":2.796158605},
{"learn":[2.356588323],"iteration":154,"passed_time":0.5118892503,"remaining_time":2.790622042},
{"learn":[2.347312266],"iteration":155,"passed_time":0.5140972618,"remaining_time":2.781398006},
{"learn":[2.337448107],"iteration":156,"passed_time":0.516878018,"remaining_time":2.775338657},
{"learn":[2.330487375],"iteration":157,"passed_time":0.5188726565,"remaining_time":2.765131498},
{"learn":[2.326412034],"iteration":158,"passed_time":0.5211268933,"remaining_time":2.756400737},
{"learn":[2.320487256],"iteration":159,"passed_time":0.5238957746,"remaining_time":2.750452817},
{"learn":[2.314751185],"iteration":160,"passed_time":0.5266903127,"remaining_time":2.744678089},
{"learn":[2.311904186],"iteration":161,"passed_time":0.5291992171,"remaining_time":2.737462617},
{"learn":[2.305881683],"iteration":162,"passed_time":0.5314771213,"remaining_time":2.729118715},
{"learn":[2.300560407],"iteration":163,"passed_time":0.533528279,"remaining_time":2.719692935},
{"learn":[2.295162299],"iteration":164,"passed_time":0.5359742965,"remaining_time":2.712354773},
{"learn":[2.289976209],"iteration":165,"passed_time":0.5387640577,"remaining_time":2.706802555},
{"learn":[2.284154147],"iteration":166,"passed_time":0.5413658151,"remaining_time":2.700345653},
{"learn":[2.279225434],"iteration":167,"passed_time":0.543653157,"remaining_time":2.692377539},
{"learn":[2.275153876],"iteration":168,"passed_time":0.5456145233,"remaining_time":2.68287378},
{"learn":[2.271142301],"iteration":169,"passed_time":0.5476355674,"remaining_time":2.673750123},
{"learn":[2.262418837],"iteration":170,"passed_time":0.5496521921,"remaining_time":2.664688112},
{"learn":[2.257050841],"iteration":171,"passed_time":0.5526068711,"remaining_time":2.660223775},
{"learn":[2.250908046],"iteration":172,"passed_time":0.5551954269,"remaining_time":2.654026694},
{"learn":[2.245154513],"iteration":173,"passed_time":0.5572840486,"remaining_time":2.64549784},
{"learn":[2.239303569],"iteration":174,"passed_time":0.5593893751,"remaining_time":2.63712134},
{"learn":[2.237219693],"iteration":175,"passed_time":0.5614025042,"remaining_time":2.628384452},
{"learn":[2.236142709],"iteration":176,"passed_time":0.5636896464,"remaining_time":2.620997621},
{"learn":[2.228625442],"iteration":177,"passed_time":0.5659812445,"remaining_time":2.613688668},
{"learn":[2.222566156],"iteration":178,"passed_time":0.5691735806,"remaining_time":2.610567093},
{"learn":[2.21724211],"iteration":179,"passed_time":0.5713246861,"remaining_time":2.602701348},
{"learn":[2.21155818],"iteration":180,"passed_time":0.5734785123,"remaining_time":2.594911058},
{"learn":[2.204667596],"iteration":181,"passed_time":0.5756516195,"remaining_time":2.587269367},
{"learn":[2.197841151],"iteration":182,"passed_time":0.5779484327,"remaining_time":2.580239724},
{"learn":[2.191131853],"iteration":183,"passed_time":0.5801297049,"remaining_time":2.572749126},
{"learn":[2.182722653],"iteration":184,"passed_time":0.5827716195,"remaining_time":2.567345242},
{"learn":[2.175829841],"iteration":185,"passed_time":0.5855118005,"remaining_time":2.562401105},
{"learn":[2.166687959],"iteration":186,"passed_time":0.587562475,"remaining_time":2.554482846},
{"learn":[2.164148671],"iteration":187,"passed_time":0.5896764738,"remaining_time":2.546900515},
{"learn":[2.160628323],"iteration":188,"passed_time":0.5916841265,"remaining_time":2.538919717},
{"learn":[2.153553822],"iteration":189,"passed_time":0.5938207907,"remaining_time":2.531551792},
{"learn":[2.149422083],"iteration":190,"passed_time":0.5967494504,"remaining_time":2.527593222},
{"learn":[2.147866165],"iteration":191,"passed_time":0.5994534786,"remaining_time":2.522700056},
{"learn":[2.141778317],"iteration":192,"passed_time":0.6017413629,"remaining_time":2.516089533},
{"learn":[2.136322303],"iteration":193,"passed_time":0.6037632557,"remaining_time":2.508418475},
{"learn":[2.13231391],"iteration":194,"passed_time":0.6056834173,"remaining_time":2.500385389},
{"learn":[2.128991859],"iteration":195,"passed_time":0.6076283311,"remaining_time":2.492516216},
{"learn":[2.125552279],"iteration":196,"passed_time":0.6103142748,"remaining_time":2.487727729},
{"learn":[2.121122146],"iteration":197,"passed_time":0.6128520679,"remaining_time":2.482360396},
{"learn":[2.117819206],"iteration":198,"passed_time":0.6149669253,"remaining_time":2.475319132},
{"learn":[2.111656249],"iteration":199,"passed_time":0.6168121201,"remaining_time":2.467248481},
{"learn":[2.109453574],"iteration":200,"passed_time":0.6188789745,"remaining_time":2.460120898},
{"learn":[2.102706451],"iteration":201,"passed_time":0.6210179883,"remaining_time":2.453328488},
{"learn":[2.096386567],"iteration":202,"passed_time":0.6229839525,"remaining_time":2.445902513},
{"learn":[2.090705448],"iteration":203,"passed_time":0.6253726644,"remaining_time":2.440179612},
{"learn":[2.087317573],"iteration":204,"passed_time":0.6274359186,"remaining_time":2.433227099},
{"learn":[2.082656335],"iteration":205,"passed_time":0.6293182262,"remaining_time":2.425624619},
{"learn":[2.080382975],"iteration":206,"passed_time":0.6312253528,"remaining_time":2.418172487},
{"learn":[2.076366916],"iteration":207,"passed_time":0.6333415133,"remaining_time":2.411569608},
{"learn":[2.070528119],"iteration":208,"passed_time":0.6358997859,"remaining_time":2.406682922},
{"learn":[2.068255601],"iteration":209,"passed_time":0.6381304893,"remaining_time":2.400586126},
{"learn":[2.064106185],"iteration":210,"passed_time":0.6408525654,"remaining_time":2.396363385},
{"learn":[2.058482849],"iteration":211,"passed_time":0.6429124382,"remaining_time":2.389693402},
{"learn":[2.052661136],"iteration":212,"passed_time":0.6447509656,"remaining_time":2.382248873},
{"learn":[2.049725166],"iteration":213,"passed_time":0.6468438341,"remaining_time":2.375790905},
{"learn":[2.04411546],"iteration":214,"passed_time":0.6488822849,"remaining_time":2.369174854},
{"learn":[2.035888863],"iteration":215,"passed_time":0.6506029918,"remaining_time":2.361447896},
{"learn":[2.031304169],"iteration":216,"passed_time":0.6526441552,"remaining_time":2.354932597},
{"learn":[2.03020168],"iteration":217,"passed_time":0.6552182067,"remaining_time":2.350369898},
{"learn":[2.027088143],"iteration":218,"passed_time":0.6571477526,"remaining_time":2.343526917},
{"learn":[2.019566076],"iteration":219,"passed_time":0.6592846336,"remaining_time":2.337463701},
{"learn":[2.018068267],"iteration":220,"passed_time":0.661088103,"remaining_time":2.330260779},
{"learn":[2.01623336],"iteration":221,"passed_time":0.6628943712,"remaining_time":2.32311631},
{"learn":[2.015105357],"iteration":222,"passed_time":0.6648194564,"remaining_time":2.316433711},
{"learn":[2.009200668],"iteration":223,"passed_time":0.6672163138,"remaining_time":2.311427944},
{"learn":[2.008193233],"iteration":224,"passed_time":0.6692756768,"remaining_time":2.305282887},
{"learn":[2.003406516],"iteration":225,"passed_time":0.671432253,"remaining_time":2.299506919},
{"learn":[1.999968638],"iteration":226,"passed_time":0.6735999964,"remaining_time":2.293800869},
{"learn":[1.996109901],"iteration":227,"passed_time":0.6762320568,"remaining_time":2.289698017},
{"learn":[1.991640594],"iteration":228,"passed_time":0.678895336,"remaining_time":2.285713118},
{"learn":[1.990998764],"iteration":229,"passed_time":0.6807410202,"remaining_time":2.279002546},
{"learn":[1.987622523],"iteration":230,"passed_time":0.6829836292,"remaining_time":2.273655458},
{"learn":[1.983176892],"iteration":231,"passed_time":0.6853205812,"remaining_time":2.268647441},
{"learn":[1.978093832],"iteration":232,"passed_time":0.6872766893,"remaining_time":2.262408672},
{"learn":[1.972982508],"iteration":233,"passed_time":0.6891756902,"remaining_time":2.256019567},
{"learn":[1.967933741],"iteration":234,"passed_time":0.6912210384,"remaining_time":2.250145082},
{"learn":[1.965466154],"iteration":235,"passed_time":0.6930352599,"remaining_time":2.243554825},
{"learn":[1.963214758],"iteration":236,"passed_time":0.6950327242,"remaining_time":2.237594804},
{"learn":[1.958212236],"iteration":237,"passed_time":0.6971929602,"remaining_time":2.232189226},
{"learn":[1.95248594],"iteration":238,"passed_time":0.6996600133,"remaining_time":2.227787741},
{"learn":[1.949170224],"iteration":239,"passed_time":0.7014448994,"remaining_time":2.221242181},
{"learn":[1.945035404],"iteration":240,"passed_time":0.7034065691,"remaining_time":2.215292888},
{"learn":[1.941975362],"iteration":241,"passed_time":0.7052013345,"remaining_time":2.208853767},
{"learn":[1.93784708],"iteration":242,"passed_time":0.7069564188,"remaining_time":2.202329255},
{"learn":[1.933868833],"iteration":243,"passed_time":0.7089573658,"remaining_time":2.196605609},
{"learn":[1.930322485],"iteration":244,"passed_time":0.7111483549,"remaining_time":2.191497992},
{"learn":[1.926338104],"iteration":245,"passed_time":0.7134585203,"remaining_time":2.186779367},
{"learn":[1.92235365],"iteration":246,"passed_time":0.7153231599,"remaining_time":2.180722022},
{"learn":[1.920337259],"iteration":247,"passed_time":0.7173619401,"remaining_time":2.175226528},
{"learn":[1.914429398],"iteration":248,"passed_time":0.71927805,"remaining_time":2.169388818},
{"learn":[1.910937512],"iteration":249,"passed_time":0.721089415,"remaining_time":2.163268245},
{"learn":[1.906141782],"iteration":250,"passed_time":0.7230116877,"remaining_time":2.157512964},
{"learn":[1.905496128],"iteration":251,"passed_time":0.7251175789,"remaining_time":2.152333131},
{"learn":[1.90429659],"iteration":252,"passed_time":0.7278197028,"remaining_time":2.148938016},
{"learn":[1.901623205],"iteration":253,"passed_time":0.7299029788,"remaining_time":2.143730796},
{"learn":[1.900805646],"iteration":254,"passed_time":0.7316486107,"remaining_time":2.137561627},
{"learn":[1.89709804],"iteration":255,"passed_time":0.7334096765,"remaining_time":2.131471872},
{"learn":[1.889862751],"iteration":256,"passed_time":0.7353652213,"remaining_time":2.125978052},
{"learn":[1.885358354],"iteration":257,"passed_time":0.7374587189,"remaining_time":2.120908409},
{"learn":[1.884513444],"iteration":258,"passed_time":0.739545942,"remaining_time":2.115843795},
{"learn":[1.879853599],"iteration":259,"passed_time":0.7423497947,"remaining_time":2.112841723},
{"learn":[1.875671796],"iteration":260,"passed_time":0.7442341679,"remaining_time":2.10723774},
{"learn":[1.870721009],"iteration":261,"passed_time":0.7460580757,"remaining_time":2.101491831},
{"learn":[1.866375326],"iteration":262,"passed_time":0.7479636881,"remaining_time":2.096004708},
{"learn":[1.862242203],"iteration":263,"passed_time":0.7499619187,"remaining_time":2.090802925},
{"learn":[1.858529378],"iteration":264,"passed_time":0.7519440206,"remaining_time":2.085580585},
{"learn":[1.853641717],"iteration":265,"passed_time":0.7539354239,"remaining_time":2.080408275},
{"learn":[1.848584335],"iteration":266,"passed_time":0.7563075229,"remaining_time":2.076304923},
{"learn":[1.845502826],"iteration":267,"passed_time":0.7585124762,"remaining_time":2.071757957},
{"learn":[1.839847521],"iteration":268,"passed_time":0.7606315634,"remaining_time":2.066995066},
{"learn":[1.838536611],"iteration":269,"passed_time":0.7625342804,"remaining_time":2.061666758},
{"learn":[1.832300776],"iteration":270,"passed_time":0.7645434004,"remaining_time":2.056649959},
{"learn":[1.828959143],"iteration":271,"passed_time":0.7664683114,"remaining_time":2.051429892},
{"learn":[1.824629321],"iteration":272,"passed_time":0.7688479889,"remaining_time":2.047445011},
{"learn":[1.820727287],"iteration":273,"passed_time":0.7711911841,"remaining_time":2.043375181},
{"learn":[1.81613261],"iteration":274,"passed_time":0.7731799055,"remaining_time":2.038383387},
{"learn":[1.81086459],"iteration":275,"passed_time":0.7751805165,"remaining_time":2.033444543},
{"learn":[1.804204189],"iteration":276,"passed_time":0.777034173,"remaining_time":2.028143347},
{"learn":[1.800114319],"iteration":277,"passed_time":0.7790059104,"remaining_time":2.023173623},
{"learn":[1.79694153],"iteration":278,"passed_time":0.7808530028,"remaining_time":2.01790328},
{"learn":[1.793531689],"iteration":279,"passed_time":0.7826977228,"remaining_time":2.012651287},
{"learn":[1.789684897],"iteration":280,"passed_time":0.78491329,"remaining_time":2.00837244},
{"learn":[1.784525698],"iteration":281,"passed_time":0.7875099567,"remaining_time":2.005078542},
{"learn":[1.780640791],"iteration":282,"passed_time":0.7893861508,"remaining_time":1.999964205},
{"learn":[1.775369721],"iteration":283,"passed_time":0.791221825,"remaining_time":1.994770517},
{"learn":[1.771841853],"iteration":284,"passed_time":0.7932106288,"remaining_time":1.98998456},
{"learn":[1.768390003],"iteration":285,"passed_time":0.7950762156,"remaining_time":1.984910552},
{"learn":[1.764881734],"iteration":286,"passed_time":0.7970287377,"remaining_time":1.980074878},
{"learn":[1.760835347],"iteration":287,"passed_time":0.7993615367,"remaining_time":1.976199355},
{"learn":[1.757594152],"iteration":288,"passed_time":0.801814612,"remaining_time":1.972630412},
{"learn":[1.75314464],"iteration":289,"passed_time":0.8037581394,"remaining_time":1.967821652},
{"learn":[1.749845351],"iteration":290,"passed_time":0.8059578061,"remaining_time":1.963656648},
{"learn":[1.747438064],"iteration":291,"passed_time":0.8079681057,"remaining_time":1.959045955},
{"learn":[1.742668829],"iteration":292,"passed_time":0.809721405,"remaining_time":1.953832878},
{"learn":[1.740884575],"iteration":293,"passed_time":0.8116777815,"remaining_time":1.949130999},
{"learn":[1.737828963],"iteration":294,"passed_time":0.8139806808,"remaining_time":1.945275864},
{"learn":[1.733156621],"iteration":295,"passed_time":0.8161943547,"remaining_time":1.941219006},
{"learn":[1.72872126],"iteration":296,"passed_time":0.8180805658,"remaining_time":1.936399454},
{"learn":[1.724087631],"iteration":297,"passed_time":0.8200953094,"remaining_time":1.931902373},
{"learn":[1.718589836],"iteration":298,"passed_time":0.8219520994,"remaining_time":1.927051577},
{"learn":[1.715654179],"iteration":299,"passed_time":0.8237846123,"remaining_time":1.922164095},
{"learn":[1.710546505],"iteration":300,"passed_time":0.8258375767,"remaining_time":1.917808858},
{"learn":[1.707078169],"iteration":301,"passed_time":0.8280782858,"remaining_time":1.913902793},
{"learn":[1.702282551],"iteration":302,"passed_time":0.8307302719,"remaining_time":1.910953794},
{"learn":[1.698503549],"iteration":303,"passed_time":0.8324969385,"remaining_time":1.905979833},
{"learn":[1.695098116],"iteration":304,"passed_time":0.8344262865,"remaining_time":1.901397604},
{"learn":[1.69248905],"iteration":305,"passed_time":0.8361752099,"remaining_time":1.896423515},
{"learn":[1.6870879],"iteration":306,"passed_time":0.8379865527,"remaining_time":1.891611339},
{"learn":[1.681515865],"iteration":307,"passed_time":0.8399419759,"remaining_time":1.887142361},
{"learn":[1.678162273],"iteration":308,"passed_time":0.8423631109,"remaining_time":1.883731099},
{"learn":[1.674482899],"iteration":309,"passed_time":0.8448737926,"remaining_time":1.880525538},
{"learn":[1.668765261],"iteration":310,"passed_time":0.8468364431,"remaining_time":1.876110319},
{"learn":[1.66493303],"iteration":311,"passed_time":0.848751461,"remaining_time":1.871605786},
{"learn":[1.658357876],"iteration":312,"passed_time":0.8505923902,"remaining_time":1.866955182},
{"learn":[1.654223788],"iteration":313,"passed_time":0.8524723562,"remaining_time":1.862407759},
{"learn":[1.651348783],"iteration":314,"passed_time":0.854223918,"remaining_time":1.857598044},
{"learn":[1.646138007],"iteration":315,"passed_time":0.8561766664,"remaining_time":1.853243164},
{"learn":[1.643390179],"iteration":316,"passed_time":0.858592839,"remaining_time":1.849901921},
{"learn":[1.637332027],"iteration":317,"passed_time":0.8607169652,"remaining_time":1.845940158},
{"learn":[1.634202863],"iteration":318,"passed_time":0.8627514367,"remaining_time":1.841798522},
{"learn":[1.629573874],"iteration":319,"passed_time":0.8648176316,"remaining_time":1.837737467},
{"learn":[1.626538534],"iteration":320,"passed_time":0.8705699501,"remaining_time":1.841485969},
{"learn":[1.623647397],"iteration":321,"passed_time":0.8743803376,"remaining_time":1.841086549},
{"learn":[1.618062953],"iteration":322,"passed_time":0.878198872,"remaining_time":1.840683085},
{"learn":[1.614555327],"iteration":323,"passed_time":0.8810070269,"remaining_time":1.838150464},
{"learn":[1.610451001],"iteration":324,"passed_time":0.8840065288,"remaining_time":1.83601356},
{"learn":[1.608227255],"iteration":325,"passed_time":0.8873673166,"remaining_time":1.834618317},
{"learn":[1.60752435],"iteration":326,"passed_time":0.8904234571,"remaining_time":1.832584057},
{"learn":[1.605104379],"iteration":327,"passed_time":0.8939867531,"remaining_time":1.831582616},
{"learn":[1.602799646],"iteration":328,"passed_time":0.8964753053,"remaining_time":1.828373647},
{"learn":[1.597510297],"iteration":329,"passed_time":0.8995007641,"remaining_time":1.826259127},
{"learn":[1.591342005],"iteration":330,"passed_time":0.9035311161,"remaining_time":1.826170141},
{"learn":[1.586075294],"iteration":331,"passed_time":0.9067487891,"remaining_time":1.824422262},
{"learn":[1.582681622],"iteration":332,"passed_time":0.9091419475,"remaining_time":1.821014051},
{"learn":[1.578572353],"iteration":333,"passed_time":0.9112193822,"remaining_time":1.816982361},
{"learn":[1.573840934],"iteration":334,"passed_time":0.91335994,"remaining_time":1.813087642},
{"learn":[1.57088764],"iteration":335,"passed_time":0.9153444109,"remaining_time":1.808894907},
{"learn":[1.56806271],"iteration":336,"passed_time":0.9190408568,"remaining_time":1.808083347},
{"learn":[1.56494657],"iteration":337,"passed_time":0.9227254107,"remaining_time":1.807231426},
{"learn":[1.562498156],"iteration":338,"passed_time":0.9255385861,"remaining_time":1.804663733},
{"learn":[1.559635022],"iteration":339,"passed_time":0.9278359039,"remaining_time":1.801093225},
{"learn":[1.555433168],"iteration":340,"passed_time":0.9304887084,"remaining_time":1.798217181},
{"learn":[1.553126898],"iteration":341,"passed_time":0.9324278642,"remaining_time":1.7939694},
{"learn":[1.550680771],"iteration":342,"passed_time":0.9344785434,"remaining_time":1.789948697},
{"learn":[1.547747031],"iteration":343,"passed_time":0.9370858458,"remaining_time":1.787000915},
{"learn":[1.545976742],"iteration":344,"passed_time":0.9391538901,"remaining_time":1.783031299},
{"learn":[1.543769935],"iteration":345,"passed_time":0.9413741499,"remaining_time":1.779360387},
{"learn":[1.53927239],"iteration":346,"passed_time":0.9438544411,"remaining_time":1.776187176},
{"learn":[1.538433067],"iteration":347,"passed_time":0.9462966922,"remaining_time":1.772946676},
{"learn":[1.533488112],"iteration":348,"passed_time":0.9482515275,"remaining_time":1.76880156},
{"learn":[1.530509557],"iteration":349,"passed_time":0.9503842139,"remaining_time":1.764999254},
{"learn":[1.528409914],"iteration":350,"passed_time":0.9523899207,"remaining_time":1.760971677},
{"learn":[1.523634331],"iteration":351,"passed_time":0.954351074,"remaining_time":1.756873568},
{"learn":[1.519754333],"iteration":352,"passed_time":0.9566955164,"remaining_time":1.753490083},
{"learn":[1.517587852],"iteration":353,"passed_time":0.9593507051,"remaining_time":1.750679535},
{"learn":[1.515315693],"iteration":354,"passed_time":0.9613466779,"remaining_time":1.746672133},
{"learn":[1.51064572],"iteration":355,"passed_time":0.9633126142,"remaining_time":1.742621695},
{"learn":[1.50722356],"iteration":356,"passed_time":0.9651446973,"remaining_time":1.73834185},
{"learn":[1.505393863],"iteration":357,"passed_time":0.9669145556,"remaining_time":1.733964091},
{"learn":[1.503101874],"iteration":358,"passed_time":0.9690010337,"remaining_time":1.730166191},
{"learn":[1.502698102],"iteration":359,"passed_time":0.9715003058,"remaining_time":1.727111655},
{"learn":[1.498956327],"iteration":360,"passed_time":0.9742331266,"remaining_time":1.724473595},
{"learn":[1.496292723],"iteration":361,"passed_time":0.9763803294,"remaining_time":1.720802901},
{"learn":[1.493477877],"iteration":362,"passed_time":0.9783961613,"remaining_time":1.716910068},
{"learn":[1.490771576],"iteration":363,"passed_time":0.9803316819,"remaining_time":1.712887224},
{"learn":[1.489726078],"iteration":364,"passed_time":0.9821305553,"remaining_time":1.708638089},
{"learn":[1.485131294],"iteration":365,"passed_time":0.9842436723,"remaining_time":1.704946689},
{"learn":[1.482376539],"iteration":366,"passed_time":0.9865438528,"remaining_time":1.701586536},
{"learn":[1.478257638],"iteration":367,"passed_time":0.9891987811,"remaining_time":1.698841385},
{"learn":[1.475413811],"iteration":368,"passed_time":0.991256424,"remaining_time":1.695075348},
{"learn":[1.472912172],"iteration":369,"passed_time":0.9933678157,"remaining_time":1.691410065},
{"learn":[1.470086528],"iteration":370,"passed_time":0.9952808168,"remaining_time":1.687416803},
{"learn":[1.468077808],"iteration":371,"passed_time":0.9973798755,"remaining_time":1.683748822},
{"learn":[1.464828164],"iteration":372,"passed_time":0.9995289291,"remaining_time":1.680173294},
{"learn":[1.463245942],"iteration":373,"passed_time":1.001774211,"remaining_time":1.676766461},
{"learn":[1.461420163],"iteration":374,"passed_time":1.004175946,"remaining_time":1.673626576},
{"learn":[1.4601553],"iteration":375,"passed_time":1.006143282,"remaining_time":1.669769702},
{"learn":[1.454784821],"iteration":376,"passed_time":1.008135004,"remaining_time":1.66596315},
{"learn":[1.452864136],"iteration":377,"passed_time":1.010161102,"remaining_time":1.662222765},
{"learn":[1.449507234],"iteration":378,"passed_time":1.011981004,"remaining_time":1.658153571},
{"learn":[1.446185577],"iteration":379,"passed_time":1.013859628,"remaining_time":1.654192024},
{"learn":[1.441843015],"iteration":380,"passed_time":1.016011085,"remaining_time":1.650684676},
{"learn":[1.441154532],"iteration":381,"passed_time":1.018481403,"remaining_time":1.64770028},
{"learn":[1.438749709],"iteration":382,"passed_time":1.020417817,"remaining_time":1.643858468},
{"learn":[1.434615971],"iteration":383,"passed_time":1.022421866,"remaining_time":1.640135076},
{"learn":[1.429231367],"iteration":384,"passed_time":1.024316852,"remaining_time":1.6362464},
{"learn":[1.42653045],"iteration":385,"passed_time":1.026182458,"remaining_time":1.63232132},
{"learn":[1.422017613],"iteration":386,"passed_time":1.028368293,"remaining_time":1.628914117},
{"learn":[1.417961377],"iteration":387,"passed_time":1.030836937,"remaining_time":1.625959292},
{"learn":[1.415817407],"iteration":388,"passed_time":1.033150078,"remaining_time":1.622762719},
{"learn":[1.415472381],"iteration":389,"passed_time":1.035095637,"remaining_time":1.61899574},
{"learn":[1.41112898],"iteration":390,"passed_time":1.036991644,"remaining_time":1.615160899},
{"learn":[1.409019917],"iteration":391,"passed_time":1.039080083,"remaining_time":1.611634415},
{"learn":[1.406958936],"iteration":392,"passed_time":1.040929097,"remaining_time":1.60774545},
{"learn":[1.405149125],"iteration":393,"passed_time":1.043048541,"remaining_time":1.604282781},
{"learn":[1.404510357],"iteration":394,"passed_time":1.045406835,"remaining_time":1.601192748},
{"learn":[1.400487716],"iteration":395,"passed_time":1.047873168,"remaining_time":1.598271195},
{"learn":[1.398703702],"iteration":396,"passed_time":1.049910341,"remaining_time":1.59470009},
{"learn":[1.395744333],"iteration":397,"passed_time":1.052025999,"remaining_time":1.591255406},
{"learn":[1.391322561],"iteration":398,"passed_time":1.053837065,"remaining_time":1.587358587},
{"learn":[1.389651276],"iteration":399,"passed_time":1.05567199,"remaining_time":1.583507985},
{"learn":[1.387074589],"iteration":400,"passed_time":1.057601339,"remaining_time":1.579808484},
{"learn":[1.386349437],"iteration":401,"passed_time":1.059645746,"remaining_time":1.576288946},
{"learn":[1.385719615],"iteration":402,"passed_time":1.062006893,"remaining_time":1.573245944},
{"learn":[1.381020829],"iteration":403,"passed_time":1.063890755,"remaining_time":1.569502203},
{"learn":[1.376156984],"iteration":404,"passed_time":1.065875112,"remaining_time":1.565915288},
{"learn":[1.37336672],"iteration":405,"passed_time":1.067782443,"remaining_time":1.562223575},
{"learn":[1.370492181],"iteration":406,"passed_time":1.069706131,"remaining_time":1.558564461},
{"learn":[1.368797912],"iteration":407,"passed_time":1.071903679,"remaining_time":1.55531122},
{"learn":[1.365735926],"iteration":408,"passed_time":1.074108248,"remaining_time":1.552073287},
{"learn":[1.362912246],"iteration":409,"passed_time":1.076620035,"remaining_time":1.549282489},
{"learn":[1.358962615],"iteration":410,"passed_time":1.078495478,"remaining_time":1.54558111},
{"learn":[1.357346433],"iteration":411,"passed_time":1.080579721,"remaining_time":1.542186592},
{"learn":[1.355658675],"iteration":412,"passed_time":1.082451606,"remaining_time":1.538496592},
{"learn":[1.355045041],"iteration":413,"passed_time":1.084226883,"remaining_time":1.534678632},
{"learn":[1.350537852],"iteration":414,"passed_time":1.086228968,"remaining_time":1.531190232},
{"learn":[1.348508368],"iteration":415,"passed_time":1.08831311,"remaining_time":1.527824174},
{"learn":[1.345561187],"iteration":416,"passed_time":1.090823227,"remaining_time":1.525059811},
{"learn":[1.342644715],"iteration":417,"passed_time":1.093169413,"remaining_time":1.522068417},
{"learn":[1.339293776],"iteration":418,"passed_time":1.095424764,"remaining_time":1.518954147},
{"learn":[1.337409847],"iteration":419,"passed_time":1.097506928,"remaining_time":1.515604805},
{"learn":[1.333616322],"iteration":420,"passed_time":1.099946053,"remaining_time":1.51275241},
{"learn":[1.331013238],"iteration":421,"passed_time":1.102106659,"remaining_time":1.509520495},
{"learn":[1.328308625],"iteration":422,"passed_time":1.105229408,"remaining_time":1.507606073},
{"learn":[1.326717535],"iteration":423,"passed_time":1.107284609,"remaining_time":1.504235696},
{"learn":[1.324968075],"iteration":424,"passed_time":1.109319639,"remaining_time":1.500844218},
{"learn":[1.321816415],"iteration":425,"passed_time":1.111329296,"remaining_time":1.49742492},
{"learn":[1.319176631],"iteration":426,"passed_time":1.113505026,"remaining_time":1.494235081},
{"learn":[1.316123766],"iteration":427,"passed_time":1.115843899,"remaining_time":1.491268015},
{"learn":[1.31464721],"iteration":428,"passed_time":1.117892714,"remaining_time":1.487917808},
{"learn":[1.312968176],"iteration":429,"passed_time":1.120098365,"remaining_time":1.484781553},
{"learn":[1.310032458],"iteration":430,"passed_time":1.121908799,"remaining_time":1.481127857},
{"learn":[1.306084037],"iteration":431,"passed_time":1.123936445,"remaining_time":1.477768289},
{"learn":[1.303319905],"iteration":432,"passed_time":1.126031551,"remaining_time":1.474503209},
{"learn":[1.300908359],"iteration":433,"passed_time":1.127902524,"remaining_time":1.470951218},
{"learn":[1.300602194],"iteration":434,"passed_time":1.129708069,"remaining_time":1.467321975},
{"learn":[1.300325968],"iteration":435,"passed_time":1.131941323,"remaining_time":1.464254371},
{"learn":[1.297333409],"iteration":436,"passed_time":1.134216258,"remaining_time":1.461244287},
{"learn":[1.296869168],"iteration":437,"passed_time":1.136118608,"remaining_time":1.457759492},
{"learn":[1.295009869],"iteration":438,"passed_time":1.138103487,"remaining_time":1.454387372},
{"learn":[1.29202436],"iteration":439,"passed_time":1.140060844,"remaining_time":1.450986529},
{"learn":[1.289762044],"iteration":440,"passed_time":1.141939037,"remaining_time":1.447491886},
{"learn":[1.287025354],"iteration":441,"passed_time":1.143907952,"remaining_time":1.444119089},
{"learn":[1.286617457],"iteration":442,"passed_time":1.145926597,"remaining_time":1.440815157},
{"learn":[1.284490538],"iteration":443,"passed_time":1.148659002,"remaining_time":1.438410823},
{"learn":[1.282664695],"iteration":444,"passed_time":1.150830247,"remaining_time":1.435305139},
{"learn":[1.281287332],"iteration":445,"passed_time":1.152958357,"remaining_time":1.432150067},
{"learn":[1.280769807],"iteration":446,"passed_time":1.154873166,"remaining_time":1.428735707},
{"learn":[1.280439182],"iteration":447,"passed_time":1.157018449,"remaining_time":1.425612018},
{"learn":[1.278357032],"iteration":448,"passed_time":1.159024558,"remaining_time":1.422321896},
{"learn":[1.275833402],"iteration":449,"passed_time":1.161124373,"remaining_time":1.419152011},
{"learn":[1.27372627],"iteration":450,"passed_time":1.163940162,"remaining_time":1.416858424},
{"learn":[1.271316232],"iteration":451,"passed_time":1.165888999,"remaining_time":1.413511441},
{"learn":[1.266946406],"iteration":452,"passed_time":1.167812727,"remaining_time":1.410140313},
{"learn":[1.264501414],"iteration":453,"passed_time":1.16997959,"remaining_time":1.407067965},
{"learn":[1.260330518],"iteration":454,"passed_time":1.17178862,"remaining_time":1.403570984},
{"learn":[1.258443954],"iteration":455,"passed_time":1.173615613,"remaining_time":1.400102836},
{"learn":[1.254856511],"iteration":456,"passed_time":1.175817661,"remaining_time":1.397087506},
{"learn":[1.252079328],"iteration":457,"passed_time":1.17855312,"remaining_time":1.394706967},
{"learn":[1.248086392],"iteration":458,"passed_time":1.180464802,"remaining_time":1.391353939},
{"learn":[1.247780523],"iteration":459,"passed_time":1.182499071,"remaining_time":1.388151083},
{"learn":[1.244776433],"iteration":460,"passed_time":1.184540474,"remaining_time":1.384961639},
{"learn":[1.244357132],"iteration":461,"passed_time":1.186456511,"remaining_time":1.381631175},
{"learn":[1.242964784],"iteration":462,"passed_time":1.188635776,"remaining_time":1.37861212},
{"learn":[1.240554697],"iteration":463,"passed_time":1.19101391,"remaining_time":1.375826414},
{"learn":[1.239350702],"iteration":464,"passed_time":1.193465429,"remaining_time":1.373126892},
{"learn":[1.235875019],"iteration":465,"passed_time":1.195582084,"remaining_time":1.370044705},
{"learn":[1.23226729],"iteration":466,"passed_time":1.197539657,"remaining_time":1.36678509},
{"learn":[1.230319987],"iteration":467,"passed_time":1.199513288,"remaining_time":1.363549293},
{"learn":[1.227196277],"iteration":468,"passed_time":1.201397494,"remaining_time":1.360217632},
{"learn":[1.224487778],"iteration":469,"passed_time":1.203461632,"remaining_time":1.357095032},
{"learn":[1.224254993],"iteration":470,"passed_time":1.20557932,"remaining_time":1.354037071},
{"learn":[1.221961996],"iteration":471,"passed_time":1.208075684,"remaining_time":1.351406697},
{"learn":[1.217660133],"iteration":472,"passed_time":1.210162562,"remaining_time":1.348320656},
{"learn":[1.213306233],"iteration":473,"passed_time":1.211933237,"remaining_time":1.344887938},
{"learn":[1.211283579],"iteration":474,"passed_time":1.213824493,"remaining_time":1.341595492},
{"learn":[1.209192603],"iteration":475,"passed_time":1.216044682,"remaining_time":1.338671036},
{"learn":[1.20766505],"iteration":476,"passed_time":1.217971032,"remaining_time":1.335427358},
{"learn":[1.206701829],"iteration":477,"passed_time":1.22015746,"remaining_time":1.33247321},
{"learn":[1.206351998],"iteration":478,"passed_time":1.222969536,"remaining_time":1.330202773},
{"learn":[1.203556864],"iteration":479,"passed_time":1.224762528,"remaining_time":1.326826072},
{"learn":[1.202583778],"iteration":480,"passed_time":1.226695179,"remaining_time":1.323606649},
{"learn":[1.199405855],"iteration":481,"passed_time":1.228585887,"remaining_time":1.320347489},
{"learn":[1.198482852],"iteration":482,"passed_time":1.230407509,"remaining_time":1.317020046},
{"learn":[1.195291663],"iteration":483,"passed_time":1.232439284,"remaining_time":1.313922873},
{"learn":[1.192460527],"iteration":484,"passed_time":1.235473418,"remaining_time":1.311894454},
{"learn":[1.191348415],"iteration":485,"passed_time":1.238568867,"remaining_time":1.309926744},
{"learn":[1.186640789],"iteration":486,"passed_time":1.241864215,"remaining_time":1.308164974},
{"learn":[1.184641763],"iteration":487,"passed_time":1.245267618,"remaining_time":1.306510288},
{"learn":[1.18212936],"iteration":488,"passed_time":1.248853133,"remaining_time":1.305038754},
{"learn":[1.178834542],"iteration":489,"passed_time":1.251862446,"remaining_time":1.302958872},
{"learn":[1.17636114],"iteration":490,"passed_time":1.254679621,"remaining_time":1.300676022},
{"learn":[1.176151723],"iteration":491,"passed_time":1.257908773,"remaining_time":1.298816376},
{"learn":[1.174343314],"iteration":492,"passed_time":1.26146403,"remaining_time":1.297286538},
{"learn":[1.172542179],"iteration":493,"passed_time":1.2646085,"remaining_time":1.295327735},
{"learn":[1.172284869],"iteration":494,"passed_time":1.26733596,"remaining_time":1.292938707},
{"learn":[1.170434812],"iteration":495,"passed_time":1.270218419,"remaining_time":1.290705813},
{"learn":[1.16721791],"iteration":496,"passed_time":1.273479202,"remaining_time":1.288853197},
{"learn":[1.164710309],"iteration":497,"passed_time":1.2779843,"remaining_time":1.288249234},
{"learn":[1.161597112],"iteration":498,"passed_time":1.280895219,"remaining_time":1.286029068},
{"learn":[1.160218487],"iteration":499,"passed_time":1.284037076,"remaining_time":1.284037076},
{"learn":[1.158163604],"iteration":500,"passed_time":1.287032337,"remaining_time":1.281894483},
{"learn":[1.156094855],"iteration":501,"passed_time":1.290565805,"remaining_time":1.280282412},
{"learn":[1.155776938],"iteration":502,"passed_time":1.293768054,"remaining_time":1.278335433},
{"learn":[1.153730767],"iteration":503,"passed_time":1.297001796,"remaining_time":1.276414466},
{"learn":[1.151864865],"iteration":504,"passed_time":1.299725271,"remaining_time":1.273988137},
{"learn":[1.14860444],"iteration":505,"passed_time":1.302489066,"remaining_time":1.271599997},
{"learn":[1.146071712],"iteration":506,"passed_time":1.306337499,"remaining_time":1.270265063},
{"learn":[1.144789733],"iteration":507,"passed_time":1.308609677,"remaining_time":1.267393624},
{"learn":[1.142681183],"iteration":508,"passed_time":1.311302505,"remaining_time":1.264930315},
{"learn":[1.139682981],"iteration":509,"passed_time":1.314298054,"remaining_time":1.262756954},
{"learn":[1.136612489],"iteration":510,"passed_time":1.317192788,"remaining_time":1.260483901},
{"learn":[1.135431947],"iteration":511,"passed_time":1.321136346,"remaining_time":1.25920808},
{"learn":[1.134424619],"iteration":512,"passed_time":1.324127619,"remaining_time":1.257017837},
{"learn":[1.1315865],"iteration":513,"passed_time":1.327316999,"remaining_time":1.255011793},
{"learn":[1.128171803],"iteration":514,"passed_time":1.329665761,"remaining_time":1.252209503},
{"learn":[1.126271383],"iteration":515,"passed_time":1.332198315,"remaining_time":1.249581365},
{"learn":[1.125866934],"iteration":516,"passed_time":1.335369352,"remaining_time":1.247550091},
{"learn":[1.123574904],"iteration":517,"passed_time":1.337987474,"remaining_time":1.244999927},
{"learn":[1.121800755],"iteration":518,"passed_time":1.34024156,"remaining_time":1.24211212},
{"learn":[1.120589445],"iteration":519,"passed_time":1.342851155,"remaining_time":1.239554913},
{"learn":[1.117578114],"iteration":520,"passed_time":1.34530648,"remaining_time":1.23685567},
{"learn":[1.115771488],"iteration":521,"passed_time":1.348683205,"remaining_time":1.235001095},
{"learn":[1.114060326],"iteration":522,"passed_time":1.352104899,"remaining_time":1.233181715},
{"learn":[1.113311936],"iteration":523,"passed_time":1.354595693,"remaining_time":1.230510592},
{"learn":[1.111574309],"iteration":524,"passed_time":1.357386273,"remaining_time":1.22811139},
{"learn":[1.108878529],"iteration":525,"passed_time":1.359982738,"remaining_time":1.225535775},
{"learn":[1.105557528],"iteration":526,"passed_time":1.362522914,"remaining_time":1.222909561},
{"learn":[1.105293729],"iteration":527,"passed_time":1.365083268,"remaining_time":1.220301709},
{"learn":[1.102576899],"iteration":528,"passed_time":1.367337104,"remaining_time":1.217421126},
{"learn":[1.099345531],"iteration":529,"passed_time":1.369617663,"remaining_time":1.214566607},
{"learn":[1.0982518],"iteration":530,"passed_time":1.371806955,"remaining_time":1.211633638},
{"learn":[1.096431085],"iteration":531,"passed_time":1.374264652,"remaining_time":1.208939581},
{"learn":[1.093441568],"iteration":532,"passed_time":1.376341891,"remaining_time":1.205913064},
{"learn":[1.090727147],"iteration":533,"passed_time":1.378851042,"remaining_time":1.203267014},
{"learn":[1.087086975],"iteration":534,"passed_time":1.380944869,"remaining_time":1.200260493},
{"learn":[1.084745127],"iteration":535,"passed_time":1.382982731,"remaining_time":1.197208932},
{"learn":[1.082774045],"iteration":536,"passed_time":1.384801071,"remaining_time":1.193971873},
{"learn":[1.080207271],"iteration":537,"passed_time":1.386898655,"remaining_time":1.190979886},
{"learn":[1.078155278],"iteration":538,"passed_time":1.388847831,"remaining_time":1.187864286},
{"learn":[1.074437945],"iteration":539,"passed_time":1.391117309,"remaining_time":1.185025856},
{"learn":[1.072785143],"iteration":540,"passed_time":1.393720113,"remaining_time":1.182472333},
{"learn":[1.070804509],"iteration":541,"passed_time":1.395775972,"remaining_time":1.179456449},
{"learn":[1.069347445],"iteration":542,"passed_time":1.397643166,"remaining_time":1.176285317},
{"learn":[1.067567327],"iteration":543,"passed_time":1.399750296,"remaining_time":1.173320101},
{"learn":[1.065126175],"iteration":544,"passed_time":1.402074079,"remaining_time":1.17053891},
{"learn":[1.063434299],"iteration":545,"passed_time":1.40425785,"remaining_time":1.167642974},
{"learn":[1.06048373],"iteration":546,"passed_time":1.406600954,"remaining_time":1.164881594},
{"learn":[1.060198604],"iteration":547,"passed_time":1.409048768,"remaining_time":1.162208108},
{"learn":[1.057228737],"iteration":548,"passed_time":1.410904741,"remaining_time":1.15904925},
{"learn":[1.054827409],"iteration":549,"passed_time":1.41268202,"remaining_time":1.155830744},
{"learn":[1.052845335],"iteration":550,"passed_time":1.414704299,"remaining_time":1.152817114},
{"learn":[1.050655972],"iteration":551,"passed_time":1.416545062,"remaining_time":1.149659761},
{"learn":[1.048498507],"iteration":552,"passed_time":1.418752233,"remaining_time":1.146803342},
{"learn":[1.046067158],"iteration":553,"passed_time":1.421399566,"remaining_time":1.144303622},
{"learn":[1.042747457],"iteration":554,"passed_time":1.423357695,"remaining_time":1.141250764},
{"learn":[1.040188139],"iteration":555,"passed_time":1.425678362,"remaining_time":1.138491354},
{"learn":[1.038787853],"iteration":556,"passed_time":1.427627899,"remaining_time":1.135438347},
{"learn":[1.038354833],"iteration":557,"passed_time":1.429408381,"remaining_time":1.132255384},
{"learn":[1.036718618],"iteration":558,"passed_time":1.431338989,"remaining_time":1.129195875},
{"learn":[1.034788537],"iteration":559,"passed_time":1.433445394,"remaining_time":1.126278524},
{"learn":[1.032011946],"iteration":560,"passed_time":1.43597197,"remaining_time":1.123692861},
{"learn":[1.030412751],"iteration":561,"passed_time":1.437966577,"remaining_time":1.120692813},
{"learn":[1.028636126],"iteration":562,"passed_time":1.440140957,"remaining_time":1.117835876},
{"learn":[1.026826389],"iteration":563,"passed_time":1.442251161,"remaining_time":1.114931749},
{"learn":[1.025453595],"iteration":564,"passed_time":1.44423127,"remaining_time":1.11193027},
{"learn":[1.024207479],"iteration":565,"passed_time":1.446174138,"remaining_time":1.108903844},
{"learn":[1.022782059],"iteration":566,"passed_time":1.448137013,"remaining_time":1.10589652},
{"learn":[1.019881398],"iteration":567,"passed_time":1.450436486,"remaining_time":1.103148877},
{"learn":[1.018044888],"iteration":568,"passed_time":1.452515884,"remaining_time":1.100236109},
{"learn":[1.017112922],"iteration":569,"passed_time":1.454386206,"remaining_time":1.097168541},
{"learn":[1.01527459],"iteration":570,"passed_time":1.456124313,"remaining_time":1.094005833},
{"learn":[1.013695358],"iteration":571,"passed_time":1.458192053,"remaining_time":1.091094753},
{"learn":[1.012108314],"iteration":572,"passed_time":1.460066228,"remaining_time":1.088042372},
{"learn":[1.009506466],"iteration":573,"passed_time":1.461946387,"remaining_time":1.084998538},
{"learn":[1.007709454],"iteration":574,"passed_time":1.464512158,"remaining_time":1.082465508},
{"learn":[1.005860822],"iteration":575,"passed_time":1.467370779,"remaining_time":1.080147935},
{"learn":[1.004478697],"iteration":576,"passed_time":1.469384161,"remaining_time":1.077208839},
{"learn":[1.002721116],"iteration":577,"passed_time":1.471178481,"remaining_time":1.074113009},
{"learn":[0.999914351],"iteration":578,"passed_time":1.473027503,"remaining_time":1.071061449},
{"learn":[0.9978511712],"iteration":579,"passed_time":1.475061211,"remaining_time":1.068147774},
{"learn":[0.9954158479],"iteration":580,"passed_time":1.477374875,"remaining_time":1.065439023},
{"learn":[0.9927854711],"iteration":581,"passed_time":1.479467231,"remaining_time":1.062572685},
{"learn":[0.9906634737],"iteration":582,"passed_time":1.482438215,"remaining_time":1.060337454},
{"learn":[0.9881999345],"iteration":583,"passed_time":1.484588726,"remaining_time":1.057515257},
{"learn":[0.9860307788],"iteration":584,"passed_time":1.486965469,"remaining_time":1.054855846},
{"learn":[0.9848545329],"iteration":585,"passed_time":1.489089217,"remaining_time":1.052018662},
{"learn":[0.9820879292],"iteration":586,"passed_time":1.491470584,"remaining_time":1.049365164},
{"learn":[0.9804205158],"iteration":587,"passed_time":1.49401803,"remaining_time":1.04682896},
{"learn":[0.9781999584],"iteration":588,"passed_time":1.496434256,"remaining_time":1.044201153},
{"learn":[0.9764123277],"iteration":589,"passed_time":1.498845838,"remaining_time":1.041570837},
{"learn":[0.974902101],"iteration":590,"passed_time":1.501115631,"remaining_time":1.038843136},
{"learn":[0.9724926971],"iteration":591,"passed_time":1.503417678,"remaining_time":1.036139211},
{"learn":[0.9717318316],"iteration":592,"passed_time":1.505820603,"remaining_time":1.033505877},
{"learn":[0.9693067669],"iteration":593,"passed_time":1.508770462,"remaining_time":1.031247151},
{"learn":[0.9677712368],"iteration":594,"passed_time":1.510948268,"remaining_time":1.028460586},
{"learn":[0.9663985938],"iteration":595,"passed_time":1.51326407,"remaining_time":1.025769604},
{"learn":[0.9646694995],"iteration":596,"passed_time":1.51537381,"remaining_time":1.02294078},
{"learn":[0.9623364105],"iteration":597,"passed_time":1.517538266,"remaining_time":1.020151142},
{"learn":[0.9616203944],"iteration":598,"passed_time":1.520277521,"remaining_time":1.01774839},
{"learn":[0.9601916941],"iteration":599,"passed_time":1.523107662,"remaining_time":1.015405108},
{"learn":[0.9578607856],"iteration":600,"passed_time":1.525609673,"remaining_time":1.012842362},
{"learn":[0.955223544],"iteration":601,"passed_time":1.527890987,"remaining_time":1.010133909},
{"learn":[0.9522622845],"iteration":602,"passed_time":1.530008729,"remaining_time":1.00731918},
{"learn":[0.9505349962],"iteration":603,"passed_time":1.53212782,"remaining_time":1.004507644},
{"learn":[0.948776643],"iteration":604,"passed_time":1.534606121,"remaining_time":1.001932922},
{"learn":[0.9472402205],"iteration":605,"passed_time":1.537309699,"remaining_time":0.9995049859},
{"learn":[0.9452461557],"iteration":606,"passed_time":1.539524232,"remaining_time":0.9967595108},
{"learn":[0.9434828959],"iteration":607,"passed_time":1.541453601,"remaining_time":0.9938319269},
{"learn":[0.9423341784],"iteration":608,"passed_time":1.54358898,"remaining_time":0.9910398867},
{"learn":[0.9403448607],"iteration":609,"passed_time":1.545831305,"remaining_time":0.9883183754},
{"learn":[0.9382241884],"iteration":610,"passed_time":1.548112842,"remaining_time":0.9856233967},
{"learn":[0.9372676222],"iteration":611,"passed_time":1.551038787,"remaining_time":0.9833383161},
{"learn":[0.9356761317],"iteration":612,"passed_time":1.553041765,"remaining_time":0.9804684551},
{"learn":[0.9336132983],"iteration":613,"passed_time":1.555045275,"remaining_time":0.9776017526},
{"learn":[0.9316197475],"iteration":614,"passed_time":1.557039189,"remaining_time":0.9747318502},
{"learn":[0.9298099248],"iteration":615,"passed_time":1.559119355,"remaining_time":0.9719185587},
{"learn":[0.9290294679],"iteration":616,"passed_time":1.560983406,"remaining_time":0.9689734921},
{"learn":[0.9266594771],"iteration":617,"passed_time":1.562975819,"remaining_time":0.9661112666},
{"learn":[0.9240352182],"iteration":618,"passed_time":1.565741623,"remaining_time":0.963727881},
{"learn":[0.9216213278],"iteration":619,"passed_time":1.56773311,"remaining_time":0.9608686806},
{"learn":[0.9200057908],"iteration":620,"passed_time":1.569747531,"remaining_time":0.9580262711},
{"learn":[0.9188207038],"iteration":621,"passed_time":1.571699555,"remaining_time":0.9551486042},
{"learn":[0.9175458915],"iteration":622,"passed_time":1.573846784,"remaining_time":0.9523920346},
{"learn":[0.9164685192],"iteration":623,"passed_time":1.576096788,"remaining_time":0.9496993465},
{"learn":[0.9154490432],"iteration":624,"passed_time":1.578599107,"remaining_time":0.947159464},
{"learn":[0.9139118471],"iteration":625,"passed_time":1.581196638,"remaining_time":0.9446765855},
{"learn":[0.912202332],"iteration":626,"passed_time":1.583135642,"remaining_time":0.9418015858},
{"learn":[0.910933311],"iteration":627,"passed_time":1.585447543,"remaining_time":0.9391504552},
{"learn":[0.9101518493],"iteration":628,"passed_time":1.587512301,"remaining_time":0.9363546322},
{"learn":[0.9085515111],"iteration":629,"passed_time":1.589381729,"remaining_time":0.9334464125},
{"learn":[0.9079626799],"iteration":630,"passed_time":1.591927483,"remaining_time":0.930936991},
{"learn":[0.9068736191],"iteration":631,"passed_time":1.594721195,"remaining_time":0.9285718348},
{"learn":[0.9054406487],"iteration":632,"passed_time":1.596744842,"remaining_time":0.9257588578},
{"learn":[0.9024785342],"iteration":633,"passed_time":1.598735676,"remaining_time":0.922929428},
{"learn":[0.9016190136],"iteration":634,"passed_time":1.600861821,"remaining_time":0.920180417},
{"learn":[0.9002124063],"iteration":635,"passed_time":1.602780349,"remaining_time":0.9173145393},
{"learn":[0.8980373759],"iteration":636,"passed_time":1.604688799,"remaining_time":0.9144458933},
{"learn":[0.8967275338],"iteration":637,"passed_time":1.60699371,"remaining_time":0.9118052084},
{"learn":[0.8952936838],"iteration":638,"passed_time":1.609457705,"remaining_time":0.9092554482},
{"learn":[0.8930132037],"iteration":639,"passed_time":1.611644855,"remaining_time":0.9065502308},
{"learn":[0.8918678602],"iteration":640,"passed_time":1.613494859,"remaining_time":0.9036578072},
{"learn":[0.8904650577],"iteration":641,"passed_time":1.61550775,"remaining_time":0.9008594616},
{"learn":[0.8890538796],"iteration":642,"passed_time":1.61751684,"remaining_time":0.8980614494},
{"learn":[0.8874457788],"iteration":643,"passed_time":1.620034532,"remaining_time":0.8955470397},
{"learn":[0.8872474393],"iteration":644,"passed_time":1.622419814,"remaining_time":0.8929597424},
{"learn":[0.8862574452],"iteration":645,"passed_time":1.624732632,"remaining_time":0.8903333616},
{"learn":[0.8848225215],"iteration":646,"passed_time":1.626880038,"remaining_time":0.8876177021},
{"learn":[0.8824441161],"iteration":647,"passed_time":1.628981049,"remaining_time":0.8848785946},
{"learn":[0.8811251453],"iteration":648,"passed_time":1.631186713,"remaining_time":0.8821980527},
{"learn":[0.8801615769],"iteration":649,"passed_time":1.637368842,"remaining_time":0.8816601455},
{"learn":[0.8779598597],"iteration":650,"passed_time":1.639421052,"remaining_time":0.8788908559},
{"learn":[0.8764191858],"iteration":651,"passed_time":1.641384048,"remaining_time":0.8760761481},
{"learn":[0.8748096351],"iteration":652,"passed_time":1.643465444,"remaining_time":0.8733269664},
{"learn":[0.8740564927],"iteration":653,"passed_time":1.645362832,"remaining_time":0.8704824768},
{"learn":[0.8725985727],"iteration":654,"passed_time":1.647253924,"remaining_time":0.867637563},
{"learn":[0.8711765101],"iteration":655,"passed_time":1.64935759,"remaining_time":0.8649070287},
{"learn":[0.8691020921],"iteration":656,"passed_time":1.652261056,"remaining_time":0.8625959548},
{"learn":[0.8679855887],"iteration":657,"passed_time":1.654225795,"remaining_time":0.8597951698},
{"learn":[0.8667885377],"iteration":658,"passed_time":1.656111991,"remaining_time":0.8569562804},
{"learn":[0.865682418],"iteration":659,"passed_time":1.658074006,"remaining_time":0.8541593366},
{"learn":[0.8641626511],"iteration":660,"passed_time":1.65993466,"remaining_time":0.8513129346},
{"learn":[0.8631000084],"iteration":661,"passed_time":1.661823627,"remaining_time":0.8484839668},
{"learn":[0.8620104419],"iteration":662,"passed_time":1.663891155,"remaining_time":0.8457485962},
{"learn":[0.8597388295],"iteration":663,"passed_time":1.666905819,"remaining_time":0.8434945107},
{"learn":[0.8581868628],"iteration":664,"passed_time":1.669012958,"remaining_time":0.8407809639},
{"learn":[0.856085306],"iteration":665,"passed_time":1.671141908,"remaining_time":0.8380801761},
{"learn":[0.8544009237],"iteration":666,"passed_time":1.673203714,"remaining_time":0.8353475815},
{"learn":[0.8529595609],"iteration":667,"passed_time":1.675039763,"remaining_time":0.8325047926},
{"learn":[0.851622626],"iteration":668,"passed_time":1.677073523,"remaining_time":0.8297628341},
{"learn":[0.8496071952],"iteration":669,"passed_time":1.679272582,"remaining_time":0.8271044063},
{"learn":[0.8482098823],"iteration":670,"passed_time":1.681919591,"remaining_time":0.8246669826},
{"learn":[0.8459282485],"iteration":671,"passed_time":1.683961644,"remaining_time":0.8219336595},
{"learn":[0.8452711219],"iteration":672,"passed_time":1.685976214,"remaining_time":0.8191890372},
{"learn":[0.8432295414],"iteration":673,"passed_time":1.687928239,"remaining_time":0.8164163292},
{"learn":[0.8425643067],"iteration":674,"passed_time":1.689806421,"remaining_time":0.8136104988},
{"learn":[0.8411602121],"iteration":675,"passed_time":1.691882976,"remaining_time":0.8109024915},
{"learn":[0.8394886411],"iteration":676,"passed_time":1.693998107,"remaining_time":0.808214754},
{"learn":[0.838066639],"iteration":677,"passed_time":1.696465725,"remaining_time":0.8056961111},
{"learn":[0.8366239674],"iteration":678,"passed_time":1.69834106,"remaining_time":0.8028976143},
{"learn":[0.8351140771],"iteration":679,"passed_time":1.700206836,"remaining_time":0.8000973344},
{"learn":[0.8343823328],"iteration":680,"passed_time":1.702160482,"remaining_time":0.79734096},
{"learn":[0.8329912673],"iteration":681,"passed_time":1.703972506,"remaining_time":0.7945209045},
{"learn":[0.8313921945],"iteration":682,"passed_time":1.705914648,"remaining_time":0.7917641923},
{"learn":[0.8304616659],"iteration":683,"passed_time":1.708315974,"remaining_time":0.7892219995},
{"learn":[0.8299362499],"iteration":684,"passed_time":1.71137734,"remaining_time":0.7869837403},
{"learn":[0.8279309145],"iteration":685,"passed_time":1.713393621,"remaining_time":0.7842647185},
{"learn":[0.8265287141],"iteration":686,"passed_time":1.71531091,"remaining_time":0.7815026419},
{"learn":[0.825064741],"iteration":687,"passed_time":1.717136874,"remaining_time":0.7787016056},
{"learn":[0.8237273715],"iteration":688,"passed_time":1.719075811,"remaining_time":0.7759543935},
{"learn":[0.8235362997],"iteration":689,"passed_time":1.721196451,"remaining_time":0.7732911592},
{"learn":[0.8221900206],"iteration":690,"passed_time":1.723437629,"remaining_time":0.7706833972},
{"learn":[0.8207814106],"iteration":691,"passed_time":1.725944241,"remaining_time":0.7681948357},
{"learn":[0.8193025776],"iteration":692,"passed_time":1.72791727,"remaining_time":0.7654698438},
{"learn":[0.8185684081],"iteration":693,"passed_time":1.729721224,"remaining_time":0.7626724704},
{"learn":[0.8168215469],"iteration":694,"passed_time":1.731576311,"remaining_time":0.7599003953},
{"learn":[0.8159762247],"iteration":695,"passed_time":1.733413655,"remaining_time":0.7571232055},
{"learn":[0.8144259293],"iteration":696,"passed_time":1.735672851,"remaining_time":0.7545321},
{"learn":[0.8126164642],"iteration":697,"passed_time":1.73782259,"remaining_time":0.7518945879},
{"learn":[0.8119279497],"iteration":698,"passed_time":1.740367847,"remaining_time":0.7494287868},
{"learn":[0.8103214348],"iteration":699,"passed_time":1.742426201,"remaining_time":0.7467540861},
{"learn":[0.8084817983],"iteration":700,"passed_time":1.74427063,"remaining_time":0.7439898979},
{"learn":[0.8076123992],"iteration":701,"passed_time":1.746012891,"remaining_time":0.7411849593},
{"learn":[0.8059301801],"iteration":702,"passed_time":1.748053256,"remaining_time":0.7385089858},
{"learn":[0.8051178618],"iteration":703,"passed_time":1.750053944,"remaining_time":0.7358181354},
{"learn":[0.8036881717],"iteration":704,"passed_time":1.752286196,"remaining_time":0.7332261388},
{"learn":[0.8018449734],"iteration":705,"passed_time":1.754873568,"remaining_time":0.730783044},
{"learn":[0.8003186903],"iteration":706,"passed_time":1.756757279,"remaining_time":0.7280479245},
{"learn":[0.8001239299],"iteration":707,"passed_time":1.758539761,"remaining_time":0.7252734608},
{"learn":[0.7983111505],"iteration":708,"passed_time":1.760230173,"remaining_time":0.722464006},
{"learn":[0.7970331528],"iteration":709,"passed_time":1.76221901,"remaining_time":0.7197795958},
{"learn":[0.7955273162],"iteration":710,"passed_time":1.764490362,"remaining_time":0.7172119755},
{"learn":[0.7943022801],"iteration":711,"passed_time":1.766426788,"remaining_time":0.714509712},
{"learn":[0.7930751765],"iteration":712,"passed_time":1.768905355,"remaining_time":0.7120278218},
{"learn":[0.79121167],"iteration":713,"passed_time":1.770801134,"remaining_time":0.709312499},
{"learn":[0.7891326819],"iteration":714,"passed_time":1.772810341,"remaining_time":0.7066446814},
{"learn":[0.7885549524],"iteration":715,"passed_time":1.77487273,"remaining_time":0.7039997981},
{"learn":[0.7878237035],"iteration":716,"passed_time":1.776964056,"remaining_time":0.7013679608},
{"learn":[0.786575643],"iteration":717,"passed_time":1.778833165,"remaining_time":0.6986503515},
{"learn":[0.7855797966],"iteration":718,"passed_time":1.781048985,"remaining_time":0.6960706045},
{"learn":[0.7840949781],"iteration":719,"passed_time":1.78364001,"remaining_time":0.6936377817},
{"learn":[0.7839206743],"iteration":720,"passed_time":1.785728195,"remaining_time":0.6910099394},
{"learn":[0.7837712492],"iteration":721,"passed_time":1.787665233,"remaining_time":0.6883253943},
{"learn":[0.7827053787],"iteration":722,"passed_time":1.789570864,"remaining_time":0.6856308845},
{"learn":[0.7824596439],"iteration":723,"passed_time":1.791331721,"remaining_time":0.6828833633},
{"learn":[0.7818754377],"iteration":724,"passed_time":1.793524766,"remaining_time":0.6803024974},
{"learn":[0.7796150935],"iteration":725,"passed_time":1.795530036,"remaining_time":0.6776518317},
{"learn":[0.7776801653],"iteration":726,"passed_time":1.798289139,"remaining_time":0.6752860177},
{"learn":[0.7763055766],"iteration":727,"passed_time":1.800290125,"remaining_time":0.6726358709},
{"learn":[0.7744217973],"iteration":728,"passed_time":1.802261302,"remaining_time":0.6699764238},
{"learn":[0.7732225348],"iteration":729,"passed_time":1.804239845,"remaining_time":0.6673215866},
{"learn":[0.7721555892],"iteration":730,"passed_time":1.805958714,"remaining_time":0.6645730424},
{"learn":[0.7707213755],"iteration":731,"passed_time":1.808098348,"remaining_time":0.6619813624},
{"learn":[0.7701435977],"iteration":732,"passed_time":1.810178534,"remaining_time":0.6593692615},
{"learn":[0.7685340456],"iteration":733,"passed_time":1.812730959,"remaining_time":0.6569297481},
{"learn":[0.76707176],"iteration":734,"passed_time":1.814665856,"remaining_time":0.6542672813},
{"learn":[0.7653863164],"iteration":735,"passed_time":1.816657786,"remaining_time":0.6516272493},
{"learn":[0.764091002],"iteration":736,"passed_time":1.818768626,"remaining_time":0.6490314093},
{"learn":[0.7628256338],"iteration":737,"passed_time":1.820736652,"remaining_time":0.6463861828},
{"learn":[0.7620103686],"iteration":738,"passed_time":1.822804996,"remaining_time":0.643778219},
{"learn":[0.760329329],"iteration":739,"passed_time":1.824715205,"remaining_time":0.6411161529},
{"learn":[0.7582176466],"iteration":740,"passed_time":1.827447815,"remaining_time":0.6387435683},
{"learn":[0.7570183331],"iteration":741,"passed_time":1.829402639,"remaining_time":0.6360995699},
{"learn":[0.7558546239],"iteration":742,"passed_time":1.831354748,"remaining_time":0.6334564874},
{"learn":[0.7556994605],"iteration":743,"passed_time":1.833173172,"remaining_time":0.6307692636},
{"learn":[0.7544824492],"iteration":744,"passed_time":1.835055643,"remaining_time":0.6281062938},
{"learn":[0.7528203223],"iteration":745,"passed_time":1.837004622,"remaining_time":0.6254680618},
{"learn":[0.7518091323],"iteration":746,"passed_time":1.838864386,"remaining_time":0.6228014588},
{"learn":[0.7495143837],"iteration":747,"passed_time":1.841173434,"remaining_time":0.6202883762},
{"learn":[0.7489015394],"iteration":748,"passed_time":1.843473203,"remaining_time":0.617772729},
{"learn":[0.74774679],"iteration":749,"passed_time":1.845336656,"remaining_time":0.6151122186},
{"learn":[0.7463259714],"iteration":750,"passed_time":1.847321158,"remaining_time":0.6124939658},
{"learn":[0.7453725082],"iteration":751,"passed_time":1.849137096,"remaining_time":0.6098218083},
{"learn":[0.7441010314],"iteration":752,"passed_time":1.851141674,"remaining_time":0.6072138028},
{"learn":[0.7434593267],"iteration":753,"passed_time":1.853226667,"remaining_time":0.6046336339},
{"learn":[0.743031076],"iteration":754,"passed_time":1.855434034,"remaining_time":0.6020944879},
{"learn":[0.7418455461],"iteration":755,"passed_time":1.857809021,"remaining_time":0.5996103188},
{"learn":[0.7415148854],"iteration":756,"passed_time":1.859993439,"remaining_time":0.5970652652},
{"learn":[0.7396677713],"iteration":757,"passed_time":1.861985602,"remaining_time":0.5944597834},
{"learn":[0.7388987354],"iteration":758,"passed_time":1.863873451,"remaining_time":0.5918227955},
{"learn":[0.7384758649],"iteration":759,"passed_time":1.865897611,"remaining_time":0.5892308246},
{"learn":[0.7368019129],"iteration":760,"passed_time":1.868130698,"remaining_time":0.5867059616},
{"learn":[0.7366740511],"iteration":761,"passed_time":1.870450032,"remaining_time":0.5842088025},
{"learn":[0.7359985684],"iteration":762,"passed_time":1.872795569,"remaining_time":0.5817202489},
{"learn":[0.7347058129],"iteration":763,"passed_time":1.874613089,"remaining_time":0.5790689645},
{"learn":[0.7333093346],"iteration":764,"passed_time":1.87649437,"remaining_time":0.576439447},
{"learn":[0.7327233712],"iteration":765,"passed_time":1.878333074,"remaining_time":0.5737988765},
{"learn":[0.7308916757],"iteration":766,"passed_time":1.880313446,"remaining_time":0.5712034328},
{"learn":[0.7301776079],"iteration":767,"passed_time":1.882336623,"remaining_time":0.5686225216},
{"learn":[0.7291379205],"iteration":768,"passed_time":1.88437119,"remaining_time":0.5660464823},
{"learn":[0.7274656971],"iteration":769,"passed_time":1.88680054,"remaining_time":0.5635897717},
{"learn":[0.7262552992],"iteration":770,"passed_time":1.888735887,"remaining_time":0.5609864048},
{"learn":[0.7253161865],"iteration":771,"passed_time":1.890655502,"remaining_time":0.5583801224},
{"learn":[0.7235801608],"iteration":772,"passed_time":1.89251749,"remaining_time":0.5557586938},
{"learn":[0.7225007351],"iteration":773,"passed_time":1.894321888,"remaining_time":0.5531224119},
{"learn":[0.720728314],"iteration":774,"passed_time":1.896251779,"remaining_time":0.5505247101},
{"learn":[0.7187945226],"iteration":775,"passed_time":1.898326115,"remaining_time":0.5479704248},
{"learn":[0.7173570657],"iteration":776,"passed_time":1.900947988,"remaining_time":0.5455745191},
{"learn":[0.7168980771],"iteration":777,"passed_time":1.902789951,"remaining_time":0.5429554874},
{"learn":[0.7155131065],"iteration":778,"passed_time":1.905229781,"remaining_time":0.5405080638},
{"learn":[0.7144688264],"iteration":779,"passed_time":1.907331879,"remaining_time":0.5379654017},
{"learn":[0.7128239087],"iteration":780,"passed_time":1.909222615,"remaining_time":0.5353646001},
{"learn":[0.7118084287],"iteration":781,"passed_time":1.911503986,"remaining_time":0.5328745128},
{"learn":[0.7101414854],"iteration":782,"passed_time":1.913804342,"remaining_time":0.53039022},
{"learn":[0.7094200805],"iteration":783,"passed_time":1.916337111,"remaining_time":0.5279704284},
{"learn":[0.7086062172],"iteration":784,"passed_time":1.918152344,"remaining_time":0.5253538267},
{"learn":[0.7067099603],"iteration":785,"passed_time":1.920000971,"remaining_time":0.5227483559},
{"learn":[0.705141154],"iteration":786,"passed_time":1.922037556,"remaining_time":0.5201956792},
{"learn":[0.7050279893],"iteration":787,"passed_time":1.924137721,"remaining_time":0.5176614174},
{"learn":[0.7036617059],"iteration":788,"passed_time":1.926117341,"remaining_time":0.5150960188},
{"learn":[0.7025230816],"iteration":789,"passed_time":1.928360421,"remaining_time":0.5126021372},
{"learn":[0.7013075561],"iteration":790,"passed_time":1.930810838,"remaining_time":0.5101636729},
{"learn":[0.7001199375],"iteration":791,"passed_time":1.932595618,"remaining_time":0.5075503642},
{"learn":[0.6984988854],"iteration":792,"passed_time":1.934591464,"remaining_time":0.504994241},
{"learn":[0.698057369],"iteration":793,"passed_time":1.936352394,"remaining_time":0.5023785809},
{"learn":[0.6979502498],"iteration":794,"passed_time":1.938735737,"remaining_time":0.4999255675},
{"learn":[0.6965893697],"iteration":795,"passed_time":1.940977115,"remaining_time":0.497436346},
{"learn":[0.695426531],"iteration":796,"passed_time":1.943218412,"remaining_time":0.4949477259},
{"learn":[0.6947766987],"iteration":797,"passed_time":1.945555631,"remaining_time":0.4924840067},
{"learn":[0.6932342837],"iteration":798,"passed_time":1.947428607,"remaining_time":0.4899038173},
{"learn":[0.692261613],"iteration":799,"passed_time":1.949417947,"remaining_time":0.4873544866},
{"learn":[0.6906682169],"iteration":800,"passed_time":1.951387296,"remaining_time":0.484801588},
{"learn":[0.6898327742],"iteration":801,"passed_time":1.953566744,"remaining_time":0.4823020142},
{"learn":[0.6884976898],"iteration":802,"passed_time":1.955606655,"remaining_time":0.4797690051},
{"learn":[0.6874336152],"iteration":803,"passed_time":1.958047766,"remaining_time":0.4773350275},
{"learn":[0.6862872084],"iteration":804,"passed_time":1.960323181,"remaining_time":0.4748608948},
{"learn":[0.6845544845],"iteration":805,"passed_time":1.962231937,"remaining_time":0.4722990022},
{"learn":[0.6834062904],"iteration":806,"passed_time":1.96414208,"remaining_time":0.4697390601},
{"learn":[0.6824482666],"iteration":807,"passed_time":1.966019107,"remaining_time":0.4671728572},
{"learn":[0.6815276598],"iteration":808,"passed_time":1.967926734,"remaining_time":0.4646155824},
{"learn":[0.6806869136],"iteration":809,"passed_time":1.970015389,"remaining_time":0.4621023751},
{"learn":[0.6798168218],"iteration":810,"passed_time":1.972255696,"remaining_time":0.4596255567},
{"learn":[0.6779652608],"iteration":811,"passed_time":1.974816495,"remaining_time":0.4572235234},
{"learn":[0.6762356392],"iteration":812,"passed_time":1.976632713,"remaining_time":0.4546498368},
{"learn":[0.6753310017],"iteration":813,"passed_time":1.978449195,"remaining_time":0.4520780715},
{"learn":[0.6739780593],"iteration":814,"passed_time":1.980311818,"remaining_time":0.4495186335},
{"learn":[0.6736831666],"iteration":815,"passed_time":1.982268404,"remaining_time":0.4469820911},
{"learn":[0.672183308],"iteration":816,"passed_time":1.984133797,"remaining_time":0.444426542},
{"learn":[0.6707971579],"iteration":817,"passed_time":1.986296156,"remaining_time":0.4419387535},
{"learn":[0.6689697362],"iteration":818,"passed_time":1.988811182,"remaining_time":0.4395296995},
{"learn":[0.6677267933],"iteration":819,"passed_time":1.990900737,"remaining_time":0.4370269911},
{"learn":[0.6668188221],"iteration":820,"passed_time":1.992893814,"remaining_time":0.4345042543},
{"learn":[0.6653573196],"iteration":821,"passed_time":1.994879829,"remaining_time":0.4319812768},
{"learn":[0.6644374776],"iteration":822,"passed_time":1.996922847,"remaining_time":0.4294718638},
{"learn":[0.6639554991],"iteration":823,"passed_time":1.998668704,"remaining_time":0.4269001114},
{"learn":[0.6634083027],"iteration":824,"passed_time":2.000878496,"remaining_time":0.4244287719},
{"learn":[0.6624698499],"iteration":825,"passed_time":2.00320248,"remaining_time":0.4219821206},
{"learn":[0.6614705816],"iteration":826,"passed_time":2.00522024,"remaining_time":0.4194717069},
{"learn":[0.6598463345],"iteration":827,"passed_time":2.007188552,"remaining_time":0.4169522114},
{"learn":[0.659321664],"iteration":828,"passed_time":2.008988329,"remaining_time":0.4143992815},
{"learn":[0.6582039413],"iteration":829,"passed_time":2.010901349,"remaining_time":0.4118713607},
{"learn":[0.6569825318],"iteration":830,"passed_time":2.013009341,"remaining_time":0.4093845712},
{"learn":[0.6562114793],"iteration":831,"passed_time":2.015258326,"remaining_time":0.4069271621},
{"learn":[0.6547408585],"iteration":832,"passed_time":2.017855261,"remaining_time":0.4045400104},
{"learn":[0.6545793864],"iteration":833,"passed_time":2.01987796,"remaining_time":0.4020380592},
{"learn":[0.6538884125],"iteration":834,"passed_time":2.021875397,"remaining_time":0.399532264},
{"learn":[0.6532983602],"iteration":835,"passed_time":2.023969652,"remaining_time":0.3970466781},
{"learn":[0.652988753],"iteration":836,"passed_time":2.026026747,"remaining_time":0.3945547906},
{"learn":[0.652369503],"iteration":837,"passed_time":2.027987817,"remaining_time":0.3920453776},
{"learn":[0.6518269399],"iteration":838,"passed_time":2.030332743,"remaining_time":0.3896109317},
{"learn":[0.6509006675],"iteration":839,"passed_time":2.032751292,"remaining_time":0.3871907222},
{"learn":[0.64947326],"iteration":840,"passed_time":2.034726546,"remaining_time":0.3846867073},
{"learn":[0.6487847814],"iteration":841,"passed_time":2.036806399,"remaining_time":0.382203576},
{"learn":[0.6477135829],"iteration":842,"passed_time":2.038608204,"remaining_time":0.379669618},
{"learn":[0.6466809541],"iteration":843,"passed_time":2.040765389,"remaining_time":0.3772030815},
{"learn":[0.6454114133],"iteration":844,"passed_time":2.042709058,"remaining_time":0.3746981112},
{"learn":[0.6439570142],"iteration":845,"passed_time":2.044846141,"remaining_time":0.3722296758},
{"learn":[0.6430656534],"iteration":846,"passed_time":2.047414241,"remaining_time":0.3698398807},
{"learn":[0.6420474551],"iteration":847,"passed_time":2.049373132,"remaining_time":0.3673404671},
{"learn":[0.641047069],"iteration":848,"passed_time":2.051459331,"remaining_time":0.3648649694},
{"learn":[0.6407519374],"iteration":849,"passed_time":2.053255852,"remaining_time":0.362339268},
{"learn":[0.640098365],"iteration":850,"passed_time":2.05528327,"remaining_time":0.3598557077},
{"learn":[0.6398138148],"iteration":851,"passed_time":2.057447821,"remaining_time":0.3573970394},
{"learn":[0.6392369762],"iteration":852,"passed_time":2.059811416,"remaining_time":0.3549733625},
{"learn":[0.6387102883],"iteration":853,"passed_time":2.062263154,"remaining_time":0.3525648952},
{"learn":[0.6378702724],"iteration":854,"passed_time":2.064193789,"remaining_time":0.3500679524},
{"learn":[0.6371344679],"iteration":855,"passed_time":2.066086506,"remaining_time":0.3475659542},
{"learn":[0.6362444385],"iteration":856,"passed_time":2.068011173,"remaining_time":0.3450707092},
{"learn":[0.6356470844],"iteration":857,"passed_time":2.070031462,"remaining_time":0.3425926197},
{"learn":[0.6353034883],"iteration":858,"passed_time":2.071915985,"remaining_time":0.3400933107},
{"learn":[0.6342619316],"iteration":859,"passed_time":2.074016345,"remaining_time":0.3376305679},
{"learn":[0.6339504819],"iteration":860,"passed_time":2.076484825,"remaining_time":0.3352280961},
{"learn":[0.6331814331],"iteration":861,"passed_time":2.078422202,"remaining_time":0.3327404453},
{"learn":[0.6323996963],"iteration":862,"passed_time":2.080336017,"remaining_time":0.3302503294},
{"learn":[0.6320249339],"iteration":863,"passed_time":2.082510171,"remaining_time":0.3278025269},
{"learn":[0.631424302],"iteration":864,"passed_time":2.084477702,"remaining_time":0.3253231095},
{"learn":[0.6307638663],"iteration":865,"passed_time":2.086347341,"remaining_time":0.3228297271},
{"learn":[0.6293782104],"iteration":866,"passed_time":2.088470707,"remaining_time":0.3203767059},
{"learn":[0.6278788311],"iteration":867,"passed_time":2.091140866,"remaining_time":0.3180075971},
{"learn":[0.62706837],"iteration":868,"passed_time":2.09299588,"remaining_time":0.315514914},
{"learn":[0.6253697854],"iteration":869,"passed_time":2.095130142,"remaining_time":0.3130654236},
{"learn":[0.6240270281],"iteration":870,"passed_time":2.096914101,"remaining_time":0.310564775},
{"learn":[0.6224301371],"iteration":871,"passed_time":2.098697982,"remaining_time":0.3080657588},
{"learn":[0.6219202981],"iteration":872,"passed_time":2.100821319,"remaining_time":0.3056177635},
{"learn":[0.6208753014],"iteration":873,"passed_time":2.103271928,"remaining_time":0.3032176921},
{"learn":[0.6199053063],"iteration":874,"passed_time":2.105650698,"remaining_time":0.3008072425},
{"learn":[0.6194208977],"iteration":875,"passed_time":2.107576166,"remaining_time":0.2983326993},
{"learn":[0.6187864133],"iteration":876,"passed_time":2.109620682,"remaining_time":0.2958761048},
{"learn":[0.6180577538],"iteration":877,"passed_time":2.111461478,"remaining_time":0.2933921417},
{"learn":[0.616623283],"iteration":878,"passed_time":2.113408583,"remaining_time":0.2909242759},
{"learn":[0.6158685779],"iteration":879,"passed_time":2.115211125,"remaining_time":0.2884378807},
{"learn":[0.615098717],"iteration":880,"passed_time":2.117499779,"remaining_time":0.2860186988},
{"learn":[0.6138396981],"iteration":881,"passed_time":2.120081651,"remaining_time":0.2836390418},
{"learn":[0.6133021509],"iteration":882,"passed_time":2.121998707,"remaining_time":0.2811708367},
{"learn":[0.6125570198],"iteration":883,"passed_time":2.124223709,"remaining_time":0.2787442876},
{"learn":[0.6116769944],"iteration":884,"passed_time":2.126310283,"remaining_time":0.2763002062},
{"learn":[0.6102011419],"iteration":885,"passed_time":2.128287387,"remaining_time":0.2738428467},
{"learn":[0.608859251],"iteration":886,"passed_time":2.130713936,"remaining_time":0.2714438273},
{"learn":[0.6075685996],"iteration":887,"passed_time":2.133291793,"remaining_time":0.2690638298},
{"learn":[0.6065957964],"iteration":888,"passed_time":2.13558188,"remaining_time":0.2666474564},
{"learn":[0.6061494937],"iteration":889,"passed_time":2.137818461,"remaining_time":0.2642247536},
{"learn":[0.6056140689],"iteration":890,"passed_time":2.14006358,"remaining_time":0.2618035132},
{"learn":[0.6044262051],"iteration":891,"passed_time":2.141948488,"remaining_time":0.2593390546},
{"learn":[0.6030237634],"iteration":892,"passed_time":2.144019321,"remaining_time":0.2568981717},
{"learn":[0.6021356023],"iteration":893,"passed_time":2.153463151,"remaining_time":0.2553323199},
{"learn":[0.6007277554],"iteration":894,"passed_time":2.156435467,"remaining_time":0.2529896358},
{"learn":[0.599213286],"iteration":895,"passed_time":2.159641872,"remaining_time":0.2506727173},
{"learn":[0.5983520571],"iteration":896,"passed_time":2.164685395,"remaining_time":0.2485647667},
{"learn":[0.5973851746],"iteration":897,"passed_time":2.168099991,"remaining_time":0.2462652551},
{"learn":[0.5961868078],"iteration":898,"passed_time":2.171160936,"remaining_time":0.2439235312},
{"learn":[0.5954644855],"iteration":899,"passed_time":2.173768406,"remaining_time":0.2415298229},
{"learn":[0.5947465544],"iteration":900,"passed_time":2.176587167,"remaining_time":0.2391588563},
{"learn":[0.5946007957],"iteration":901,"passed_time":2.180022384,"remaining_time":0.2368538733},
{"learn":[0.5935550793],"iteration":902,"passed_time":2.182628521,"remaining_time":0.2344573272},
{"learn":[0.5924048494],"iteration":903,"passed_time":2.185147996,"remaining_time":0.2320511146},
{"learn":[0.5921753963],"iteration":904,"passed_time":2.187413766,"remaining_time":0.2296180196},
{"learn":[0.5914311856],"iteration":905,"passed_time":2.189635382,"remaining_time":0.2271807129},
{"learn":[0.5911278226],"iteration":906,"passed_time":2.191728609,"remaining_time":0.2247307173},
{"learn":[0.5901838483],"iteration":907,"passed_time":2.193773389,"remaining_time":0.2222765988},
{"learn":[0.5891504888],"iteration":908,"passed_time":2.196685025,"remaining_time":0.2199101621},
{"learn":[0.5881956718],"iteration":909,"passed_time":2.200341934,"remaining_time":0.2176162352},
{"learn":[0.5876697815],"iteration":910,"passed_time":2.203331104,"remaining_time":0.2152540815},
{"learn":[0.587065527],"iteration":911,"passed_time":2.205959478,"remaining_time":0.2128557391},
{"learn":[0.5867510444],"iteration":912,"passed_time":2.207974812,"remaining_time":0.210398476},
{"learn":[0.5863429202],"iteration":913,"passed_time":2.210433877,"remaining_time":0.2079839316},
{"learn":[0.5855460154],"iteration":914,"passed_time":2.212633518,"remaining_time":0.2055451902},
{"learn":[0.5845648117],"iteration":915,"passed_time":2.214623008,"remaining_time":0.2030876994},
{"learn":[0.5835598276],"iteration":916,"passed_time":2.216941217,"remaining_time":0.2006609826},
{"learn":[0.5830037527],"iteration":917,"passed_time":2.21928963,"remaining_time":0.1982372},
{"learn":[0.5822806145],"iteration":918,"passed_time":2.221529926,"remaining_time":0.1958040522},
{"learn":[0.5820174898],"iteration":919,"passed_time":2.223438625,"remaining_time":0.1933424891},
{"learn":[0.5817760957],"iteration":920,"passed_time":2.225625462,"remaining_time":0.1909059843},
{"learn":[0.5806593801],"iteration":921,"passed_time":2.227568461,"remaining_time":0.1884493926},
{"learn":[0.5795987467],"iteration":922,"passed_time":2.229743572,"remaining_time":0.1860132774},
{"learn":[0.5788485437],"iteration":923,"passed_time":2.232278337,"remaining_time":0.1836073091},
{"learn":[0.5779763418],"iteration":924,"passed_time":2.234792179,"remaining_time":0.1811993658},
{"learn":[0.5772348429],"iteration":925,"passed_time":2.236929805,"remaining_time":0.1787611291},
{"learn":[0.5762592859],"iteration":926,"passed_time":2.238880187,"remaining_time":0.1763087957},
{"learn":[0.5753612064],"iteration":927,"passed_time":2.240702202,"remaining_time":0.1738475846},
{"learn":[0.5744106443],"iteration":928,"passed_time":2.242808135,"remaining_time":0.1714094484},
{"learn":[0.5735114985],"iteration":929,"passed_time":2.244998455,"remaining_time":0.1689783784},
{"learn":[0.5724805738],"iteration":930,"passed_time":2.247216706,"remaining_time":0.1665498955},
{"learn":[0.5720687805],"iteration":931,"passed_time":2.250015358,"remaining_time":0.1641642107},
{"learn":[0.5713215694],"iteration":932,"passed_time":2.251886409,"remaining_time":0.1617110283},
{"learn":[0.5698366321],"iteration":933,"passed_time":2.253959753,"remaining_time":0.1592733872},
{"learn":[0.5685331099],"iteration":934,"passed_time":2.255995783,"remaining_time":0.1568339314},
{"learn":[0.5679227982],"iteration":935,"passed_time":2.25788498,"remaining_time":0.1543852978},
{"learn":[0.5671103822],"iteration":936,"passed_time":2.260658336,"remaining_time":0.1519973054},
{"learn":[0.5661896297],"iteration":937,"passed_time":2.263156011,"remaining_time":0.1495902694},
{"learn":[0.5650675723],"iteration":938,"passed_time":2.266002219,"remaining_time":0.147205682},
{"learn":[0.5642757909],"iteration":939,"passed_time":2.268003072,"remaining_time":0.1447661535},
{"learn":[0.5637116456],"iteration":940,"passed_time":2.270166411,"remaining_time":0.1423377452},
{"learn":[0.5626057556],"iteration":941,"passed_time":2.272254056,"remaining_time":0.1399052391},
{"learn":[0.5618675751],"iteration":942,"passed_time":2.27414885,"remaining_time":0.1374618075},
{"learn":[0.5615141631],"iteration":943,"passed_time":2.276272451,"remaining_time":0.1350331115},
{"learn":[0.5607848559],"iteration":944,"passed_time":2.27882797,"remaining_time":0.1326301993},
{"learn":[0.5596115386],"iteration":945,"passed_time":2.280985835,"remaining_time":0.1302042654},
{"learn":[0.5593284384],"iteration":946,"passed_time":2.283088234,"remaining_time":0.1277757934},
{"learn":[0.558324725],"iteration":947,"passed_time":2.285350202,"remaining_time":0.1253567622},
{"learn":[0.5578824517],"iteration":948,"passed_time":2.287267533,"remaining_time":0.1229195408},
{"learn":[0.5574074763],"iteration":949,"passed_time":2.289619148,"remaining_time":0.1205062709},
{"learn":[0.5562191452],"iteration":950,"passed_time":2.291842688,"remaining_time":0.1180865318},
{"learn":[0.5552182162],"iteration":951,"passed_time":2.294448852,"remaining_time":0.1156864967},
{"learn":[0.5546157707],"iteration":952,"passed_time":2.296442049,"remaining_time":0.1132557989},
{"learn":[0.5534667489],"iteration":953,"passed_time":2.29830796,"remaining_time":0.1108198807},
{"learn":[0.5530397032],"iteration":954,"passed_time":2.300411569,"remaining_time":0.1083963567},
{"learn":[0.5525741298],"iteration":955,"passed_time":2.302448843,"remaining_time":0.1059704489},
{"learn":[0.552242249],"iteration":956,"passed_time":2.304596654,"remaining_time":0.1035503199},
{"learn":[0.551479479],"iteration":957,"passed_time":2.306813383,"remaining_time":0.1011337809},
{"learn":[0.5503607268],"iteration":958,"passed_time":2.30901793,"remaining_time":0.0987171378},
{"learn":[0.5494845913],"iteration":959,"passed_time":2.311452707,"remaining_time":0.09631052945},
{"learn":[0.5487924265],"iteration":960,"passed_time":2.313624016,"remaining_time":0.09389317027},
{"learn":[0.5479302667],"iteration":961,"passed_time":2.315521822,"remaining_time":0.09146551896},
{"learn":[0.5470085145],"iteration":962,"passed_time":2.31778747,"remaining_time":0.08905310114},
{"learn":[0.5463504901],"iteration":963,"passed_time":2.320000102,"remaining_time":0.08663900797},
{"learn":[0.5452791959],"iteration":964,"passed_time":2.322277765,"remaining_time":0.08422769097},
{"learn":[0.5444991777],"iteration":965,"passed_time":2.324935878,"remaining_time":0.08183004126},
{"learn":[0.5436597597],"iteration":966,"passed_time":2.327343047,"remaining_time":0.07942328909},
{"learn":[0.5424746666],"iteration":967,"passed_time":2.329407176,"remaining_time":0.0770051959},
{"learn":[0.5419897176],"iteration":968,"passed_time":2.331608441,"remaining_time":0.07459222049},
{"learn":[0.5416440266],"iteration":969,"passed_time":2.333711552,"remaining_time":0.07217664595},
{"learn":[0.5408909764],"iteration":970,"passed_time":2.335641308,"remaining_time":0.06975653751},
{"learn":[0.5394843551],"iteration":971,"passed_time":2.337712104,"remaining_time":0.06734150094},
{"learn":[0.5391870238],"iteration":972,"passed_time":2.340689858,"remaining_time":0.06495233932},
{"learn":[0.5384145033],"iteration":973,"passed_time":2.342964555,"remaining_time":0.06254320168},
{"learn":[0.5375161525],"iteration":974,"passed_time":2.345076555,"remaining_time":0.06013016808},
{"learn":[0.5366031634],"iteration":975,"passed_time":2.347534449,"remaining_time":0.05772625695},
{"learn":[0.5358760052],"iteration":976,"passed_time":2.3503634,"remaining_time":0.05533097052},
{"learn":[0.5346994625],"iteration":977,"passed_time":2.353038342,"remaining_time":0.05293133285},
{"learn":[0.5336082959],"iteration":978,"passed_time":2.355252599,"remaining_time":0.05052125085},
{"learn":[0.5326829168],"iteration":979,"passed_time":2.357534687,"remaining_time":0.04811295279},
{"learn":[0.5320198701],"iteration":980,"passed_time":2.359497395,"remaining_time":0.0456987263},
{"learn":[0.5316915491],"iteration":981,"passed_time":2.361963278,"remaining_time":0.04329464257},
{"learn":[0.5313943221],"iteration":982,"passed_time":2.364509277,"remaining_time":0.04089181863},
{"learn":[0.5303773682],"iteration":983,"passed_time":2.367243658,"remaining_time":0.03849176679},
{"learn":[0.5300776287],"iteration":984,"passed_time":2.369424077,"remaining_time":0.03608260016},
{"learn":[0.5289300721],"iteration":985,"passed_time":2.371580458,"remaining_time":0.0336735562},
{"learn":[0.5283391451],"iteration":986,"passed_time":2.373630768,"remaining_time":0.03126362714},
{"learn":[0.5275504434],"iteration":987,"passed_time":2.375824896,"remaining_time":0.02885617283},
{"learn":[0.5263070764],"iteration":988,"passed_time":2.37800961,"remaining_time":0.02644904521},
{"learn":[0.5253089558],"iteration":989,"passed_time":2.380373782,"remaining_time":0.02404417962},
{"learn":[0.5249660809],"iteration":990,"passed_time":2.382454741,"remaining_time":0.02163682408},
{"learn":[0.5242552714],"iteration":991,"passed_time":2.38452428,"remaining_time":0.01923003451},
{"learn":[0.5236811936],"iteration":992,"passed_time":2.394600131,"remaining_time":0.01688036346},
{"learn":[0.5231884179],"iteration":993,"passed_time":2.397405817,"remaining_time":0.01447126248},
{"learn":[0.5224853914],"iteration":994,"passed_time":2.40031034,"remaining_time":0.01206186101},
{"learn":[0.5223518056],"iteration":995,"passed_time":2.403991272,"remaining_time":0.009654583423},
{"learn":[0.52178531],"iteration":996,"passed_time":2.407652342,"remaining_time":0.007244691099},
{"learn":[0.5211397624],"iteration":997,"passed_time":2.410733278,"remaining_time":0.004831128813},
{"learn":[0.5210043656],"iteration":998,"passed_time":2.413809927,"remaining_time":0.002416226153},
{"learn":[0.5200170284],"iteration":999,"passed_time":2.417008814,"remaining_time":0}
]}